src/alu.sv
`default_nettype none
`timescale 1ns/1ns

module alu(
    input wire clock,                              // Clock signal - heartbeat of the circuit
    input wire reset,                            // Reset everything to 0
    input wire enable,                           // Is this ALU active? (some threads may be inactive)
    input wire [2:0] core_state,                  // 3-bit state: which stage is the core in?
    input wire [1:0] decoded_alu_arithmetic_selector,  // 2-bit: which operation? (ADD/SUB/MUL/DIV)
    input wire decoded_alu_output_selector,            // 1-bit: arithmetic or comparison?
    input wire [7:0] rs,                          // 8-bit: first operand (source register 1)
    input wire [7:0] rt,                          // 8-bit: second operand (source register 2)
    output wire [7:0] alu_out                    
);

localparam ADD = 2'b00,      // 00 in binary = ADD
           SUB = 2'b01,      // 01 = SUB
           MUL = 2'b10,      // 10 = MUL
           DIV = 2'b11;      // 11 = DIV

    // Internal register to hold ALU output
    reg [7:0] alu_out_reg;
    assign alu_out = alu_out_reg;

    // 16-bit product to detect MUL overflow before truncating to 8 bits
    wire [15:0] mul_wide = {8'b0, rs} * {8'b0, rt};

    // EXECUTE stage state (from core_state)
    localparam EXECUTE = 3'b101;

    always @(posedge clock) begin
        if (reset) begin
            alu_out_reg <= 8'b0;
        end else if (enable) begin
            // Perform computation only in EXECUTE stage
            if (core_state == EXECUTE) begin
                if (decoded_alu_output_selector == 1'b1) begin
                    // Comparison mode: set NZP flags in alu_out[2:0]
                    // [2] = negative, [1] = zero, [0] = positive
                    alu_out_reg <= {5'b0,
                                   (rs < rt),      // negative (rs - rt < 0)
                                   (rs == rt),     // zero     (rs - rt == 0)
                                   (rs > rt)};     // positive (rs - rt > 0)
                end else begin
                    // Arithmetic mode: execute ADD/SUB/MUL/DIV
                    case (decoded_alu_arithmetic_selector)
                        ADD: alu_out_reg <= rs + rt;
                        SUB: alu_out_reg <= rs - rt;
                        MUL: alu_out_reg <= mul_wide[15:8] ? 8'hFF : mul_wide[7:0];  // saturate at 255 on overflow
                        DIV: alu_out_reg <= rs / rt;
                        default: alu_out_reg <= 8'bx;
                    endcase
                end
            end
        end
    end

endmodule

test/alu_tb.sv
`default_nettype none
`timescale 1ns/1ns

module alu_tb;
    // Testbench signals
    reg clock;
    reg reset;
    reg enable;
    reg [2:0] core_state;
    reg [1:0] decoded_alu_arithmetic_selector;
    reg decoded_alu_output_selector;
    reg [7:0] rs;
    reg [7:0] rt;
    wire [7:0] alu_out;

    // Instantiate the ALU
    alu uut (
        .clock(clock),
        .reset(reset),
        .enable(enable),
        .core_state(core_state),
        .decoded_alu_arithmetic_selector(decoded_alu_arithmetic_selector),
        .decoded_alu_output_selector(decoded_alu_output_selector),
        .rs(rs),
        .rt(rt),
        .alu_out(alu_out)
    );

    // Clock generation: 10ns period (100MHz)
    always #5 clock = ~clock;

    // State parameters
    localparam EXECUTE = 3'b101;

    // ALU operation parameters
    localparam ADD = 2'b00;
    localparam SUB = 2'b01;
    localparam MUL = 2'b10;
    localparam DIV = 2'b11;

    // Test counter
    integer tests_passed = 0;
    integer tests_failed = 0;

    // Task to check result
    task check_result;
        input [7:0] expected;
        input [255:0] test_name;  // String for test name
        begin
            if (alu_out === expected) begin
                $display("[PASS] %s: got %d", test_name, alu_out);
                tests_passed = tests_passed + 1;
            end else begin
                $display("[FAIL] %s: expected %d, got %d", test_name, expected, alu_out);
                tests_failed = tests_failed + 1;
            end
        end
    endtask

    initial begin
        // Setup waveform dump
        $dumpfile("alu_tb.vcd");
        $dumpvars(0, alu_tb);

        // Initialize signals
        clock = 0;
        reset = 1;
        enable = 0;
        core_state = 3'b000;
        decoded_alu_arithmetic_selector = 2'b00;
        decoded_alu_output_selector = 0;
        rs = 8'b0;
        rt = 8'b0;

        $display("\n========================================");
        $display("ALU Testbench Starting");
        $display("========================================\n");

        // Reset sequence
        #20;
        reset = 0;
        enable = 1;
        core_state = EXECUTE;
        #10;

        // ==========================================
        // Test Arithmetic Operations
        // ==========================================
        $display("--- Testing Arithmetic Operations ---\n");

        // Test ADD: 5 + 3 = 8
        decoded_alu_output_selector = 0;  // Arithmetic mode
        decoded_alu_arithmetic_selector = ADD;
        rs = 8'd5;
        rt = 8'd3;
        #10;
        check_result(8'd8, "ADD: 5 + 3");

        // Test ADD: 100 + 55 = 155
        rs = 8'd100;
        rt = 8'd55;
        #10;
        check_result(8'd155, "ADD: 100 + 55");

        // Test ADD overflow: 200 + 100 = 44 (wraps around)
        rs = 8'd200;
        rt = 8'd100;
        #10;
        check_result(8'd44, "ADD overflow: 200 + 100");

        // Test SUB: 10 - 3 = 7
        decoded_alu_arithmetic_selector = SUB;
        rs = 8'd10;
        rt = 8'd3;
        #10;
        check_result(8'd7, "SUB: 10 - 3");

        // Test SUB underflow: 3 - 10 = 249 (wraps around)
        rs = 8'd3;
        rt = 8'd10;
        #10;
        check_result(8'd249, "SUB underflow: 3 - 10");

        // Test MUL: 6 * 7 = 42
        decoded_alu_arithmetic_selector = MUL;
        rs = 8'd6;
        rt = 8'd7;
        #10;
        check_result(8'd42, "MUL: 6 * 7");

        // Test MUL: 15 * 15 = 225
        rs = 8'd15;
        rt = 8'd15;
        #10;
        check_result(8'd225, "MUL: 15 * 15");

        // Test DIV: 20 / 4 = 5
        decoded_alu_arithmetic_selector = DIV;
        rs = 8'd20;
        rt = 8'd4;
        #10;
        check_result(8'd5, "DIV: 20 / 4");

        // Test DIV: 100 / 7 = 14 (integer division)
        rs = 8'd100;
        rt = 8'd7;
        #10;
        check_result(8'd14, "DIV: 100 / 7");

        // ==========================================
        // Test Comparison Operations
        // ==========================================
        $display("\n--- Testing Comparison Operations ---\n");
        decoded_alu_output_selector = 1;  // Comparison mode

        // Test: rs < rt (5 < 10) -> negative flag set
        rs = 8'd5;
        rt = 8'd10;
        #10;
        check_result(8'b00000100, "CMP: 5 < 10 (N=1,Z=0,P=0)");

        // Test: rs == rt (7 == 7) -> zero flag set
        rs = 8'd7;
        rt = 8'd7;
        #10;
        check_result(8'b00000010, "CMP: 7 == 7 (N=0,Z=1,P=0)");

        // Test: rs > rt (15 > 8) -> positive flag set
        rs = 8'd15;
        rt = 8'd8;
        #10;
        check_result(8'b00000001, "CMP: 15 > 8 (N=0,Z=0,P=1)");

        // ==========================================
        // Test Enable Signal
        // ==========================================
        $display("\n--- Testing Enable Signal ---\n");

        // Disable ALU and change inputs - output should not change
        enable = 0;
        decoded_alu_output_selector = 0;
        decoded_alu_arithmetic_selector = ADD;
        rs = 8'd50;
        rt = 8'd50;
        #10;
        // Output should still be from previous test (comparison result)
        check_result(8'b00000001, "Enable=0: Output unchanged");

        // Re-enable and verify it works again
        enable = 1;
        #10;
        check_result(8'd100, "Enable=1: ADD 50 + 50");

        // ==========================================
        // Test Core State
        // ==========================================
        $display("\n--- Testing Core State ---\n");

        // Set to non-EXECUTE state - output should not change
        core_state = 3'b000;  // Not EXECUTE
        rs = 8'd1;
        rt = 8'd1;
        #10;
        check_result(8'd100, "Non-EXECUTE state: Output unchanged");

        // Return to EXECUTE state
        core_state = EXECUTE;
        #10;
        check_result(8'd2, "EXECUTE state: ADD 1 + 1");

        // ==========================================
        // Test Reset
        // ==========================================
        $display("\n--- Testing Reset ---\n");

        reset = 1;
        #10;
        check_result(8'd0, "Reset: Output = 0");
        reset = 0;

        // ==========================================
        // Summary
        // ==========================================
        #20;
        $display("\n========================================");
        $display("Test Summary");
        $display("========================================");
        $display("Passed: %d", tests_passed);
        $display("Failed: %d", tests_failed);
        $display("========================================\n");

        if (tests_failed == 0) begin
            $display("ALL TESTS PASSED!\n");
        end else begin
            $display("SOME TESTS FAILED!\n");
        end

        $finish;
    end

endmodule

test/alu_tb.vcd
$date
	Sat Mar  7 20:28:13 2026
$end
$version
	Icarus Verilog
$end
$timescale
	1ns
$end
$scope module alu_tb $end
$var wire 8 ! alu_out [7:0] $end
$var parameter 2 " ADD $end
$var parameter 2 # DIV $end
$var parameter 3 $ EXECUTE $end
$var parameter 2 % MUL $end
$var parameter 2 & SUB $end
$var reg 1 ' clock $end
$var reg 3 ( core_state [2:0] $end
$var reg 2 ) decoded_alu_arithmetic_selector [1:0] $end
$var reg 1 * decoded_alu_output_selector $end
$var reg 1 + enable $end
$var reg 1 , reset $end
$var reg 8 - rs [7:0] $end
$var reg 8 . rt [7:0] $end
$var integer 32 / tests_failed [31:0] $end
$var integer 32 0 tests_passed [31:0] $end
$scope module uut $end
$var wire 8 1 alu_out [7:0] $end
$var wire 1 ' clock $end
$var wire 3 2 core_state [2:0] $end
$var wire 2 3 decoded_alu_arithmetic_selector [1:0] $end
$var wire 1 * decoded_alu_output_selector $end
$var wire 1 + enable $end
$var wire 1 , reset $end
$var wire 8 4 rs [7:0] $end
$var wire 8 5 rt [7:0] $end
$var wire 16 6 mul_wide [15:0] $end
$var parameter 2 7 ADD $end
$var parameter 2 8 DIV $end
$var parameter 3 9 EXECUTE $end
$var parameter 2 : MUL $end
$var parameter 2 ; SUB $end
$var reg 8 < alu_out_reg [7:0] $end
$upscope $end
$scope task check_result $end
$var reg 8 = expected [7:0] $end
$var reg 256 > test_name [255:0] $end
$upscope $end
$upscope $end
$enddefinitions $end
$comment Show the parameter values. $end
$dumpall
b1 ;
b10 :
b101 9
b11 8
b0 7
b1 &
b10 %
b101 $
b11 #
b0 "
$end
#0
$dumpvars
bx >
bx =
bx <
b0 6
b0 5
b0 4
b0 3
b0 2
bx 1
b0 0
b0 /
b0 .
b0 -
1,
0+
0*
b0 )
b0 (
0'
bx !
$end
#5
b0 !
b0 1
b0 <
1'
#10
0'
#15
1'
#20
0'
b101 (
b101 2
1+
0,
#25
1'
#30
0'
b1111 6
b11 .
b11 5
b101 -
b101 4
#35
b1000 !
b1000 1
b1000 <
1'
#40
0'
b110111 .
b110111 5
b1010101111100 6
b1100100 -
b1100100 4
b1 0
b1000001010001000100010000111010001000000011010100100000001010110010000000110011 >
b1000 =
#45
b10011011 !
b10011011 1
b10011011 <
1'
#50
0'
b1100100 .
b1100100 5
b100111000100000 6
b11001000 -
b11001000 4
b10 0
b1000001010001000100010000111010001000000011000100110000001100000010000000101011001000000011010100110101 >
b10011011 =
#55
b101100 !
b101100 1
b101100 <
1'
#60
0'
b11 .
b11 5
b11110 6
b1010 -
b1010 4
b1 )
b1 3
b11 0
b100000101000100010001000010000001101111011101100110010101110010011001100110110001101111011101110011101000100000001100100011000000110000001000000010101100100000001100010011000000110000 >
b101100 =
#65
b111 !
b111 1
b111 <
1'
#70
0'
b1010 .
b1010 5
b11110 6
b11 -
b11 4
b100 0
b101001101010101010000100011101000100000001100010011000000100000001011010010000000110011 >
b111 =
#75
b11111001 !
b11111001 1
b11111001 <
1'
#80
0'
b111 .
b111 5
b101010 6
b110 -
b110 4
b10 )
b10 3
b101 0
b10100110101010101000010001000000111010101101110011001000110010101110010011001100110110001101111011101110011101000100000001100110010000000101101001000000011000100110000 >
b11111001 =
#85
b101010 !
b101010 1
b101010 <
1'
#90
0'
b1111 .
b1111 5
b11100001 6
b1111 -
b1111 4
b110 0
b1001101010101010100110000111010001000000011011000100000001010100010000000110111 >
b101010 =
#95
b11100001 !
b11100001 1
b11100001 <
1'
#100
0'
b100 .
b100 5
b1010000 6
b10100 -
b10100 4
b11 )
b11 3
b111 0
b10011010101010101001100001110100010000000110001001101010010000000101010001000000011000100110101 >
b11100001 =
#105
b101 !
b101 1
b101 <
1'
#110
0'
b111 .
b111 5
b1010111100 6
b1100100 -
b1100100 4
b1000 0
b100010001001001010101100011101000100000001100100011000000100000001011110010000000110100 >
b101 =
#115
b1110 !
b1110 1
b1110 <
1'
#120
0'
b1010 .
b1010 5
b110010 6
b101 -
b101 4
1*
b1001 0
b10001000100100101010110001110100010000000110001001100000011000000100000001011110010000000110111 >
b1110 =
#125
b100 !
b100 1
b100 <
1'
#130
0'
b111 .
b111 5
b110001 6
b111 -
b111 4
b1010 0
b1000011010011010101000000111010001000000011010100100000001111000010000000110001001100000010000000101000010011100011110100110001001011000101101000111101001100000010110001010000001111010011000000101001 >
b100 =
#135
b10 !
b10 1
b10 <
1'
#140
0'
b1000 .
b1000 5
b1111000 6
b1111 -
b1111 4
b1011 0
b1000011010011010101000000111010001000000011011100100000001111010011110100100000001101110010000000101000010011100011110100110000001011000101101000111101001100010010110001010000001111010011000000101001 >
b10 =
#145
b1 !
b1 1
b1 <
1'
#150
0'
b110010 .
b110010 5
b100111000100 6
b110010 -
b110010 4
b0 )
b0 3
0*
0+
b1100 0
b1000011010011010101000000111010001000000011000100110101001000000011111000100000001110000010000000101000010011100011110100110000001011000101101000111101001100000010110001010000001111010011000100101001 >
b1 =
#155
1'
#160
0'
1+
b1101 0
b100010101101110011000010110001001101100011001010011110100110000001110100010000001001111011101010111010001110000011101010111010000100000011101010110111001100011011010000110000101101110011001110110010101100100 >
#165
b1100100 !
b1100100 1
b1100100 <
1'
#170
0'
b1 .
b1 5
b1 6
b1 -
b1 4
b0 (
b0 2
b1110 0
b10001010110111001100001011000100110110001100101001111010011000100111010001000000100000101000100010001000010000000110101001100000010000000101011001000000011010100110000 >
b1100100 =
#175
1'
#180
0'
b101 (
b101 2
b1111 0
b10110101000101010110000100010101000011010101010101010001000101001000000111001101110100011000010111010001100101001110100010000001001111011101010111010001110000011101010111010000100000011101010110111001100011011010000110000101101110011001110110010101100100 >
#185
b10 !
b10 1
b10 <
1'
#190
0'
1,
b10000 0
b10001010101100001000101010000110101010101010100010001010010000001110011011101000110000101110100011001010011101000100000010000010100010001000100001000000011000100100000001010110010000000110001 >
b10 =
#195
b0 !
b0 1
b0 <
1'
#200
0'
0,
b10001 0
b101001001100101011100110110010101110100001110100010000001001111011101010111010001110000011101010111010000100000001111010010000000110000 >
b0 =
#205
b10 !
b10 1
b10 <
1'
