src/controller.sv
`default_nettype none
`timescale 1ns/1ns

// MEMORY CONTROLLER
// Arbitrates many consumer request channels onto a smaller number of physical
// memory channels. Each physical channel runs an independent little FSM:
//   1. IDLE          - pick a pending consumer request (lowest index first)
//   2. READ/WRITE_WAITING  - forward it to memory, wait for ready
//   3. READ/WRITE_RELAYING - hand the response back, wait for the consumer to ack
//   4. back to IDLE  - free the channel (and the consumer) for the next request
//
// Used twice in the GPU: once for program memory (consumers = core fetchers,
// read-only in practice) and once for data memory (consumers = thread LSUs,
// read + write). A `consumer_busy` scoreboard stops two channels grabbing the
// same consumer in the same cycle.
//
// Per-consumer / per-channel buses are FLATTENED into packed vectors (consumer
// k's address = consumer_read_address[k*ADDR_BITS +: ADDR_BITS]). This keeps the
// module portable across simulators that dislike unpacked array ports.
module controller #(
    parameter ADDR_BITS     = 8,
    parameter DATA_BITS     = 16,
    parameter NUM_CONSUMERS = 4,    // request channels coming in (>= 2)
    parameter NUM_CHANNELS  = 1     // physical memory channels going out
) (
    input  wire clock,
    input  wire reset,

    // ----- Consumer side (requests in from cores) -----
    input  wire [NUM_CONSUMERS-1:0]           consumer_read_valid,
    input  wire [NUM_CONSUMERS*ADDR_BITS-1:0] consumer_read_address,
    output reg  [NUM_CONSUMERS-1:0]           consumer_read_ready,
    output reg  [NUM_CONSUMERS*DATA_BITS-1:0] consumer_read_data,
    input  wire [NUM_CONSUMERS-1:0]           consumer_write_valid,
    input  wire [NUM_CONSUMERS*ADDR_BITS-1:0] consumer_write_address,
    input  wire [NUM_CONSUMERS*DATA_BITS-1:0] consumer_write_data,
    output reg  [NUM_CONSUMERS-1:0]           consumer_write_ready,

    // ----- Memory side (forwarded to actual memory) -----
    output reg  [NUM_CHANNELS-1:0]            mem_read_valid,
    output reg  [NUM_CHANNELS*ADDR_BITS-1:0]  mem_read_address,
    input  wire [NUM_CHANNELS-1:0]            mem_read_ready,
    input  wire [NUM_CHANNELS*DATA_BITS-1:0]  mem_read_data,
    output reg  [NUM_CHANNELS-1:0]            mem_write_valid,
    output reg  [NUM_CHANNELS*ADDR_BITS-1:0]  mem_write_address,
    output reg  [NUM_CHANNELS*DATA_BITS-1:0]  mem_write_data,
    input  wire [NUM_CHANNELS-1:0]            mem_write_ready
);

    // Width needed to name a consumer
    localparam CONSUMER_IDX_BITS = $clog2(NUM_CONSUMERS);

    // Per-channel arbitration FSM
    localparam IDLE           = 3'b000,
               READ_WAITING   = 3'b001,
               WRITE_WAITING  = 3'b010,
               READ_RELAYING  = 3'b011,
               WRITE_RELAYING = 3'b100;

    // Internal unpacked arrays are fine (only *ports* are flattened)
    reg [2:0]                   channel_state    [NUM_CHANNELS-1:0];
    reg [CONSUMER_IDX_BITS-1:0] current_consumer [NUM_CHANNELS-1:0];

    // Scoreboard: which consumers are already claimed by some channel.
    // BLOCKING-assigned so claims/releases are visible to later channels within
    // the same clock evaluation (prevents double-serving).
    reg [NUM_CONSUMERS-1:0] consumer_busy;

    integer c;      // channel index
    integer k;      // consumer index
    reg     found;  // "this channel claimed a consumer this cycle"

    always @(posedge clock) begin
        if (reset) begin
            consumer_read_ready  <= {NUM_CONSUMERS{1'b0}};
            consumer_write_ready <= {NUM_CONSUMERS{1'b0}};
            consumer_read_data   <= {(NUM_CONSUMERS*DATA_BITS){1'b0}};
            mem_read_valid       <= {NUM_CHANNELS{1'b0}};
            mem_write_valid      <= {NUM_CHANNELS{1'b0}};
            mem_read_address     <= {(NUM_CHANNELS*ADDR_BITS){1'b0}};
            mem_write_address    <= {(NUM_CHANNELS*ADDR_BITS){1'b0}};
            mem_write_data       <= {(NUM_CHANNELS*DATA_BITS){1'b0}};
            consumer_busy         = {NUM_CONSUMERS{1'b0}};
            for (c = 0; c < NUM_CHANNELS; c = c + 1) begin
                channel_state[c]    <= IDLE;
                current_consumer[c] <= {CONSUMER_IDX_BITS{1'b0}};
            end
        end else begin
            for (c = 0; c < NUM_CHANNELS; c = c + 1) begin
                case (channel_state[c])
                    IDLE: begin
                        // Serve the lowest-index pending request that no other
                        // channel has already claimed this cycle.
                        found = 1'b0;
                        for (k = 0; k < NUM_CONSUMERS; k = k + 1) begin
                            if (!found && !consumer_busy[k]) begin
                                if (consumer_read_valid[k]) begin
                                    found                = 1'b1;
                                    consumer_busy[k]      = 1'b1;
                                    current_consumer[c]  <= k[CONSUMER_IDX_BITS-1:0];
                                    mem_read_valid[c]    <= 1'b1;
                                    mem_read_address[c*ADDR_BITS +: ADDR_BITS]
                                        <= consumer_read_address[k*ADDR_BITS +: ADDR_BITS];
                                    channel_state[c]     <= READ_WAITING;
                                end else if (consumer_write_valid[k]) begin
                                    found                = 1'b1;
                                    consumer_busy[k]      = 1'b1;
                                    current_consumer[c]  <= k[CONSUMER_IDX_BITS-1:0];
                                    mem_write_valid[c]   <= 1'b1;
                                    mem_write_address[c*ADDR_BITS +: ADDR_BITS]
                                        <= consumer_write_address[k*ADDR_BITS +: ADDR_BITS];
                                    mem_write_data[c*DATA_BITS +: DATA_BITS]
                                        <= consumer_write_data[k*DATA_BITS +: DATA_BITS];
                                    channel_state[c]     <= WRITE_WAITING;
                                end
                            end
                        end
                    end

                    READ_WAITING: begin
                        // Forwarded read is in flight; relay the data when it lands
                        if (mem_read_ready[c]) begin
                            mem_read_valid[c]                       <= 1'b0;
                            consumer_read_ready[current_consumer[c]] <= 1'b1;
                            consumer_read_data[current_consumer[c]*DATA_BITS +: DATA_BITS]
                                <= mem_read_data[c*DATA_BITS +: DATA_BITS];
                            channel_state[c]                        <= READ_RELAYING;
                        end
                    end

                    WRITE_WAITING: begin
                        if (mem_write_ready[c]) begin
                            mem_write_valid[c]                        <= 1'b0;
                            consumer_write_ready[current_consumer[c]] <= 1'b1;
                            channel_state[c]                          <= WRITE_RELAYING;
                        end
                    end

                    READ_RELAYING: begin
                        // Hold the response until the consumer drops its request,
                        // then release the consumer and free the channel.
                        if (!consumer_read_valid[current_consumer[c]]) begin
                            consumer_busy[current_consumer[c]]       = 1'b0;
                            consumer_read_ready[current_consumer[c]] <= 1'b0;
                            channel_state[c]                         <= IDLE;
                        end
                    end

                    WRITE_RELAYING: begin
                        if (!consumer_write_valid[current_consumer[c]]) begin
                            consumer_busy[current_consumer[c]]        = 1'b0;
                            consumer_write_ready[current_consumer[c]] <= 1'b0;
                            channel_state[c]                          <= IDLE;
                        end
                    end
                endcase
            end
        end
    end

endmodule

test/controller_tb.sv
`default_nettype none
`timescale 1ns/1ns

// CONTROLLER TESTBENCH
// Drives several consumer request channels at a single physical memory channel
// and checks the controller relays each request/response correctly and
// serializes simultaneous requests through the one channel.
//
// Buses are flattened: consumer k lives in [k*W +: W] of each packed vector.
module controller_tb;
    localparam ADDR_BITS     = 8;
    localparam DATA_BITS     = 8;
    localparam NUM_CONSUMERS = 4;
    localparam NUM_CHANNELS  = 1;

    reg clock;
    reg reset;

    // Consumer side (driven by the test)
    reg  [NUM_CONSUMERS-1:0]           consumer_read_valid;
    reg  [NUM_CONSUMERS*ADDR_BITS-1:0] consumer_read_address;
    wire [NUM_CONSUMERS-1:0]           consumer_read_ready;
    wire [NUM_CONSUMERS*DATA_BITS-1:0] consumer_read_data;
    reg  [NUM_CONSUMERS-1:0]           consumer_write_valid;
    reg  [NUM_CONSUMERS*ADDR_BITS-1:0] consumer_write_address;
    reg  [NUM_CONSUMERS*DATA_BITS-1:0] consumer_write_data;
    wire [NUM_CONSUMERS-1:0]           consumer_write_ready;

    // Memory side (answered by the mock memory)
    wire [NUM_CHANNELS-1:0]           mem_read_valid;
    wire [NUM_CHANNELS*ADDR_BITS-1:0] mem_read_address;
    reg  [NUM_CHANNELS-1:0]           mem_read_ready;
    reg  [NUM_CHANNELS*DATA_BITS-1:0] mem_read_data;
    wire [NUM_CHANNELS-1:0]           mem_write_valid;
    wire [NUM_CHANNELS*ADDR_BITS-1:0] mem_write_address;
    wire [NUM_CHANNELS*DATA_BITS-1:0] mem_write_data;
    reg  [NUM_CHANNELS-1:0]           mem_write_ready;

    controller #(
        .ADDR_BITS     (ADDR_BITS),
        .DATA_BITS     (DATA_BITS),
        .NUM_CONSUMERS (NUM_CONSUMERS),
        .NUM_CHANNELS  (NUM_CHANNELS)
    ) uut (
        .clock                  (clock),
        .reset                  (reset),
        .consumer_read_valid    (consumer_read_valid),
        .consumer_read_address  (consumer_read_address),
        .consumer_read_ready    (consumer_read_ready),
        .consumer_read_data     (consumer_read_data),
        .consumer_write_valid   (consumer_write_valid),
        .consumer_write_address (consumer_write_address),
        .consumer_write_data    (consumer_write_data),
        .consumer_write_ready   (consumer_write_ready),
        .mem_read_valid         (mem_read_valid),
        .mem_read_address       (mem_read_address),
        .mem_read_ready         (mem_read_ready),
        .mem_read_data          (mem_read_data),
        .mem_write_valid        (mem_write_valid),
        .mem_write_address      (mem_write_address),
        .mem_write_data         (mem_write_data),
        .mem_write_ready        (mem_write_ready)
    );

    always #5 clock = ~clock;

    // ----- Mock memory (single channel, 1-cycle latency) -----
    reg [7:0] data_mem [0:255];
    integer rcnt = 0;
    integer wcnt = 0;
    always @(posedge clock) begin
        if (reset) begin
            mem_read_ready[0]  <= 0; mem_read_data[0*DATA_BITS +: DATA_BITS] <= 0; rcnt <= 0;
            mem_write_ready[0] <= 0; wcnt <= 0;
        end else begin
            if (mem_read_valid[0] && !mem_read_ready[0]) begin
                if (rcnt >= 1) begin
                    mem_read_ready[0] <= 1;
                    mem_read_data[0*DATA_BITS +: DATA_BITS]
                        <= data_mem[mem_read_address[0*ADDR_BITS +: ADDR_BITS]];
                    rcnt <= 0;
                end else rcnt <= rcnt + 1;
            end else begin
                mem_read_ready[0] <= 0; rcnt <= 0;
            end

            if (mem_write_valid[0] && !mem_write_ready[0]) begin
                if (wcnt >= 1) begin
                    mem_write_ready[0] <= 1;
                    data_mem[mem_write_address[0*ADDR_BITS +: ADDR_BITS]]
                        <= mem_write_data[0*DATA_BITS +: DATA_BITS];
                    wcnt <= 0;
                end else wcnt <= wcnt + 1;
            end else begin
                mem_write_ready[0] <= 0; wcnt <= 0;
            end
        end
    end

    integer tests_passed = 0;
    integer tests_failed = 0;
    integer k, guard, served;
    reg [7:0] captured [NUM_CONSUMERS-1:0];

    task check_signal;
        input integer actual;
        input integer expected;
        input [255:0] label;
        begin
            if (actual === expected) begin
                $display("[PASS] %s", label);
                tests_passed = tests_passed + 1;
            end else begin
                $display("[FAIL] %s: expected %0d, got %0d", label, expected, actual);
                tests_failed = tests_failed + 1;
            end
        end
    endtask

    initial begin
        $dumpfile("controller_tb.vcd");
        $dumpvars(0, controller_tb);

        // Preload memory
        data_mem[8'h10] = 8'h42;
        data_mem[8'h20] = 8'hA0;
        data_mem[8'h21] = 8'hA1;
        data_mem[8'h22] = 8'hA2;
        data_mem[8'h23] = 8'hA3;

        clock = 0;
        reset = 1;
        consumer_read_valid    = {NUM_CONSUMERS{1'b0}};
        consumer_write_valid   = {NUM_CONSUMERS{1'b0}};
        consumer_read_address  = 0;
        consumer_write_address = 0;
        consumer_write_data    = 0;
        mem_read_ready  = 0;
        mem_write_ready = 0;
        for (k = 0; k < NUM_CONSUMERS; k = k + 1) captured[k] = 8'hxx;

        $display("\n========================================");
        $display("Controller Testbench Starting");
        $display("========================================\n");

        #20;
        check_signal(consumer_read_ready,  0, "Reset: consumer_read_ready = 0");
        check_signal(consumer_write_ready, 0, "Reset: consumer_write_ready = 0");
        check_signal(mem_read_valid,       0, "Reset: mem_read_valid = 0");
        reset = 0;
        #10;

        // ==========================================
        // Single consumer read
        // ==========================================
        $display("\n--- Single consumer read ---\n");

        consumer_read_address[0*ADDR_BITS +: ADDR_BITS] = 8'h10;
        consumer_read_valid[0]                          = 1;
        guard = 0;
        while (!consumer_read_ready[0] && guard < 100) begin #10; guard = guard + 1; end
        check_signal(consumer_read_data[0*DATA_BITS +: DATA_BITS], data_mem[8'h10],
                     "consumer 0 read [0x10] = 0x42");
        consumer_read_valid[0] = 0;     // acknowledge
        #20;

        // ==========================================
        // All consumers request at once -> serialized through 1 channel
        // ==========================================
        $display("\n--- Simultaneous reads (arbitration) ---\n");

        for (k = 0; k < NUM_CONSUMERS; k = k + 1) begin
            consumer_read_address[k*ADDR_BITS +: ADDR_BITS] = 8'h20 + k[7:0];
            consumer_read_valid[k]                          = 1;
        end

        served = 0;
        guard  = 0;
        while (served < NUM_CONSUMERS && guard < 400) begin
            for (k = 0; k < NUM_CONSUMERS; k = k + 1) begin
                if (consumer_read_valid[k] && consumer_read_ready[k]) begin
                    captured[k]            = consumer_read_data[k*DATA_BITS +: DATA_BITS];
                    consumer_read_valid[k] = 0;     // ack, freeing the channel
                    served                 = served + 1;
                end
            end
            #10; guard = guard + 1;
        end

        check_signal(served,      NUM_CONSUMERS, "all 4 consumers served");
        check_signal(captured[0], 8'hA0, "consumer 0 got [0x20] = 0xA0");
        check_signal(captured[1], 8'hA1, "consumer 1 got [0x21] = 0xA1");
        check_signal(captured[2], 8'hA2, "consumer 2 got [0x22] = 0xA2");
        check_signal(captured[3], 8'hA3, "consumer 3 got [0x23] = 0xA3");
        #20;

        // ==========================================
        // A consumer write
        // ==========================================
        $display("\n--- Consumer write ---\n");

        consumer_write_address[1*ADDR_BITS +: ADDR_BITS] = 8'h30;
        consumer_write_data[1*DATA_BITS +: DATA_BITS]    = 8'h77;
        consumer_write_valid[1]                          = 1;
        guard = 0;
        while (!consumer_write_ready[1] && guard < 100) begin #10; guard = guard + 1; end
        consumer_write_valid[1] = 0;
        #20;
        check_signal(data_mem[8'h30], 8'h77, "consumer 1 wrote 0x77 -> [0x30]");

        // ==========================================
        // Summary
        // ==========================================
        #20;
        $display("\n========================================");
        $display("Test Summary");
        $display("========================================");
        $display("Passed: %d", tests_passed);
        $display("Failed: %d", tests_failed);
        $display("========================================\n");

        if (tests_failed == 0)
            $display("ALL TESTS PASSED!\n");
        else
            $display("SOME TESTS FAILED!\n");

        $finish;
    end

endmodule

test/controller_tb.vcd
$date
	Sat Jun  6 10:48:15 2026
$end
$version
	Icarus Verilog
$end
$timescale
	1ns
$end
$scope module controller_tb $end
$var wire 1 ! mem_write_valid $end
$var wire 8 " mem_write_data [7:0] $end
$var wire 8 # mem_write_address [7:0] $end
$var wire 1 $ mem_read_valid $end
$var wire 8 % mem_read_address [7:0] $end
$var wire 4 & consumer_write_ready [3:0] $end
$var wire 4 ' consumer_read_ready [3:0] $end
$var wire 32 ( consumer_read_data [31:0] $end
$var parameter 32 ) ADDR_BITS $end
$var parameter 32 * DATA_BITS $end
$var parameter 32 + NUM_CHANNELS $end
$var parameter 32 , NUM_CONSUMERS $end
$var reg 1 - clock $end
$var reg 32 . consumer_read_address [31:0] $end
$var reg 4 / consumer_read_valid [3:0] $end
$var reg 32 0 consumer_write_address [31:0] $end
$var reg 32 1 consumer_write_data [31:0] $end
$var reg 4 2 consumer_write_valid [3:0] $end
$var reg 8 3 mem_read_data [7:0] $end
$var reg 1 4 mem_read_ready $end
$var reg 1 5 mem_write_ready $end
$var reg 1 6 reset $end
$var integer 32 7 guard [31:0] $end
$var integer 32 8 k [31:0] $end
$var integer 32 9 rcnt [31:0] $end
$var integer 32 : served [31:0] $end
$var integer 32 ; tests_failed [31:0] $end
$var integer 32 < tests_passed [31:0] $end
$var integer 32 = wcnt [31:0] $end
$scope module uut $end
$var wire 1 - clock $end
$var wire 32 > consumer_read_address [31:0] $end
$var wire 4 ? consumer_read_valid [3:0] $end
$var wire 32 @ consumer_write_address [31:0] $end
$var wire 32 A consumer_write_data [31:0] $end
$var wire 4 B consumer_write_valid [3:0] $end
$var wire 8 C mem_read_data [7:0] $end
$var wire 1 4 mem_read_ready $end
$var wire 1 5 mem_write_ready $end
$var wire 1 6 reset $end
$var parameter 32 D ADDR_BITS $end
$var parameter 32 E CONSUMER_IDX_BITS $end
$var parameter 32 F DATA_BITS $end
$var parameter 3 G IDLE $end
$var parameter 32 H NUM_CHANNELS $end
$var parameter 32 I NUM_CONSUMERS $end
$var parameter 3 J READ_RELAYING $end
$var parameter 3 K READ_WAITING $end
$var parameter 3 L WRITE_RELAYING $end
$var parameter 3 M WRITE_WAITING $end
$var reg 4 N consumer_busy [3:0] $end
$var reg 32 O consumer_read_data [31:0] $end
$var reg 4 P consumer_read_ready [3:0] $end
$var reg 4 Q consumer_write_ready [3:0] $end
$var reg 1 R found $end
$var reg 8 S mem_read_address [7:0] $end
$var reg 1 $ mem_read_valid $end
$var reg 8 T mem_write_address [7:0] $end
$var reg 8 U mem_write_data [7:0] $end
$var reg 1 ! mem_write_valid $end
$var integer 32 V c [31:0] $end
$var integer 32 W k [31:0] $end
$upscope $end
$scope task check_signal $end
$var reg 256 X label [255:0] $end
$var integer 32 Y actual [31:0] $end
$var integer 32 Z expected [31:0] $end
$upscope $end
$upscope $end
$enddefinitions $end
$comment Show the parameter values. $end
$dumpall
b10 M
b100 L
b1 K
b11 J
b100 I
b1 H
b0 G
b1000 F
b10 E
b1000 D
b100 ,
b1 +
b1000 *
b1000 )
$end
#0
$dumpvars
bx Z
bx Y
bx X
bx W
bx V
bx U
bx T
bx S
xR
bx Q
bx P
bx O
bx N
bx C
b0 B
b0 A
b0 @
b0 ?
b0 >
b0 =
b0 <
b0 ;
bx :
b0 9
b100 8
bx 7
16
05
04
bx 3
b0 2
b0 1
b0 0
b0 /
b0 .
0-
bx (
bx '
bx &
bx %
x$
bx #
bx "
x!
$end
#5
b0 "
b0 U
b0 #
b0 T
b0 %
b0 S
0!
0$
b0 (
b0 O
b0 &
b0 Q
b0 '
b0 P
b0 3
b0 C
b1 V
b0 N
1-
#10
0-
#15
b1 V
1-
#20
0-
06
b11 <
b1010010011001010111001101100101011101000011101000100000011011010110010101101101010111110111001001100101011000010110010001011111011101100110000101101100011010010110010000100000001111010010000000110000 X
b0 Z
b0 Y
#25
b100 W
0R
b1 V
1-
#30
0-
b0 7
b1 /
b1 ?
b10000 .
b10000 >
#35
b10000 %
b10000 S
1$
b1 N
1R
b100 W
b1 V
1-
#40
0-
b1 7
#45
b1 9
b1 V
1-
#50
0-
b10 7
#55
b0 9
b1000010 3
b1000010 C
14
b1 V
1-
#60
0-
b11 7
#65
b1000010 (
b1000010 O
b1 '
b1 P
0$
04
b1 V
1-
#70
0-
b0 /
b0 ?
b100 <
b110001101101111011011100111001101110101011011010110010101110010001000000011000000100000011100100110010101100001011001000010000001011011001100000111100000110001001100000101110100100000001111010010000000110000011110000011010000110010 X
b1000010 Z
b1000010 Y
b100 7
#75
b0 '
b0 P
b0 N
b1 V
1-
#80
0-
#85
b100 W
0R
b1 V
1-
#90
0-
b0 7
b0 :
b1111 /
b1111 ?
b100011001000100010000100100000 .
b100011001000100010000100100000 >
b100 8
#95
b100000 %
b100000 S
1$
b1 N
1R
b100 W
b1 V
1-
#100
0-
b100 8
b1 7
#105
b1 9
b1 V
1-
#110
0-
b100 8
b10 7
#115
b0 9
b10100000 3
b10100000 C
14
b1 V
1-
#120
0-
b100 8
b11 7
#125
b10100000 (
b10100000 O
b1 '
b1 P
0$
04
b1 V
1-
#130
0-
b1 :
b1110 /
b1110 ?
b100 8
b100 7
#135
b0 '
b0 P
b0 N
b1 V
1-
#140
0-
b100 8
b101 7
#145
b100001 %
b100001 S
1$
b10 N
b100 W
1R
b1 V
1-
#150
0-
b100 8
b110 7
#155
b1 9
b1 V
1-
#160
0-
b100 8
b111 7
#165
b0 9
b10100001 3
b10100001 C
14
b1 V
1-
#170
0-
b100 8
b1000 7
#175
04
b1010000110100000 (
b1010000110100000 O
b10 '
b10 P
0$
b1 V
1-
#180
0-
b10 :
b1100 /
b1100 ?
b100 8
b1001 7
#185
b0 '
b0 P
b0 N
b1 V
1-
#190
0-
b100 8
b1010 7
#195
b100010 %
b100010 S
1$
b100 N
b100 W
1R
b1 V
1-
#200
0-
b100 8
b1011 7
#205
b1 9
b1 V
1-
#210
0-
b100 8
b1100 7
#215
b0 9
b10100010 3
b10100010 C
14
b1 V
1-
#220
0-
b100 8
b1101 7
#225
b101000101010000110100000 (
b101000101010000110100000 O
b100 '
b100 P
0$
04
b1 V
1-
#230
0-
b11 :
b1000 /
b1000 ?
b100 8
b1110 7
#235
b0 '
b0 P
b0 N
b1 V
1-
#240
0-
b100 8
b1111 7
#245
b100011 %
b100011 S
1$
b1000 N
b100 W
1R
b1 V
1-
#250
0-
b100 8
b10000 7
#255
b1 9
b1 V
1-
#260
0-
b100 8
b10001 7
#265
b0 9
b10100011 3
b10100011 C
14
b1 V
1-
#270
0-
b100 8
b10010 7
#275
04
b10100011101000101010000110100000 (
b10100011101000101010000110100000 O
b1000 '
b1000 P
0$
b1 V
1-
#280
0-
b100 :
b0 /
b0 ?
b100 8
b10011 7
#285
b0 '
b0 P
b0 N
b1 V
1-
#290
0-
b1001 <
b1100011011011110110111001110011011101010110110101100101011100100010000000110011001000000110011101101111011101000010000001011011001100000111100000110010001100110101110100100000001111010010000000110000011110000100000100110011 X
b10100011 Z
b10100011 Y
b10100 7
#295
b100 W
0R
b1 V
1-
#300
0-
#305
b100 W
b1 V
1-
#310
0-
b0 7
b10 2
b10 B
b111011100000000 1
b111011100000000 A
b11000000000000 0
b11000000000000 @
#315
b1110111 "
b1110111 U
b110000 #
b110000 T
1!
b10 N
1R
b100 W
b1 V
1-
#320
0-
b1 7
#325
b1 =
b1 V
1-
#330
0-
b10 7
#335
b0 =
15
b1 V
1-
#340
0-
b11 7
#345
b10 &
b10 Q
0!
05
b1 V
1-
#350
0-
b0 2
b0 B
b100 7
#355
b0 &
b0 Q
b0 N
b1 V
1-
#360
0-
#365
b100 W
0R
b1 V
1-
#370
0-
b1010 <
b1100011011011110110111001110011011101010110110101100101011100100010000000110001001000000111011101110010011011110111010001100101001000000011000001111000001101110011011100100000001011010011111000100000010110110011000001111000001100110011000001011101 X
b1110111 Z
b1110111 Y
#375
b100 W
b1 V
1-
#380
0-
#385
b100 W
b1 V
1-
