src/decoder.sv
`default_nettype none
`timescale 1ns/1ns

// INSTRUCTION DECODER
// > Decodes a 16-bit instruction into control signals for the rest of the pipeline
// > Runs in the DECODE stage - one decoder shared across all threads in a core
// > Outputs are held until the next DECODE stage
module decoder (
    input wire clock,                                   // Clock signal - heartbeat of the circuit
    input wire reset,                                   // Reset all outputs to 0

    input wire [2:0] core_state,                         // 3-bit state: which pipeline stage is active?
    input wire [15:0] instruction,                       // 16-bit instruction word fetched from program memory

    // Instruction Fields (extracted bit slices)
    output reg [3:0] decoded_rd_address,                // 4-bit: destination register address (bits [11:8])
    output reg [3:0] decoded_rs_address,                // 4-bit: source register 1 address (bits [7:4])
    output reg [3:0] decoded_rt_address,                // 4-bit: source register 2 address (bits [3:0])
    output reg [2:0] decoded_nzp,                       // 3-bit: NZP condition mask for BRnzp (bits [11:9])
    output reg [7:0] decoded_immediate,                 // 8-bit: immediate/constant value (bits [7:0])

    // Control Signals
    output reg decoded_reg_write_enable,                // 1-bit: should we write a result back to rd?
    output reg decoded_mem_read_enable,                 // 1-bit: should we issue a memory read (LDR)?
    output reg decoded_mem_write_enable,                // 1-bit: should we issue a memory write (STR)?
    output reg decoded_nzp_write_enable,                // 1-bit: should we update the NZP condition register?
    output reg [1:0] decoded_reg_input_selector,        // 2-bit: which result to write into rd? (ALU / memory / immediate)
    output reg [1:0] decoded_alu_arithmetic_selector,   // 2-bit: which arithmetic op should the ALU perform?
    output reg decoded_alu_output_selector,             // 1-bit: ALU in arithmetic mode (0) or comparison mode (1)?
    output reg decoded_pc_mux,                          // 1-bit: next PC from increment (0) or branch target (1)?

    // Thread Termination
    output reg decoded_ret                              // 1-bit: this thread is done executing (RET instruction)
);

    // Instruction opcodes - top 4 bits [15:12] of the instruction word
    localparam NOP   = 4'b0000,   // No operation
               BRnzp = 4'b0001,   // Conditional branch based on NZP flags
               CMP   = 4'b0010,   // Compare rs and rt, write NZP flags
               ADD   = 4'b0011,   // rd = rs + rt
               SUB   = 4'b0100,   // rd = rs - rt
               MUL   = 4'b0101,   // rd = rs * rt
               DIV   = 4'b0110,   // rd = rs / rt
               LDR   = 4'b0111,   // rd = memory[rs]
               STR   = 4'b1000,   // memory[rs] = rt
               CONST = 4'b1001,   // rd = immediate
               RET   = 4'b1111;   // Signal thread completion

    // Register write source selection (matches decoded_reg_input_selector encoding)
    localparam REG_SRC_ARITHMETIC = 2'b00,   // Write ALU arithmetic/comparison result
               REG_SRC_MEMORY     = 2'b01,   // Write memory load result (LDR)
               REG_SRC_CONSTANT   = 2'b10;   // Write immediate value (CONST)

    // ALU arithmetic operation selection (matches decoded_alu_arithmetic_selector encoding)
    localparam ALU_ADD = 2'b00,
               ALU_SUB = 2'b01,
               ALU_MUL = 2'b10,
               ALU_DIV = 2'b11;

    // Pipeline stage we care about
    localparam DECODE = 3'b010;   // Decoder is active during stage 2

    always @(posedge clock) begin
        if (reset) begin
            decoded_rd_address            <= 4'b0;
            decoded_rs_address            <= 4'b0;
            decoded_rt_address            <= 4'b0;
            decoded_nzp                   <= 3'b0;
            decoded_immediate             <= 8'b0;
            decoded_reg_write_enable      <= 1'b0;
            decoded_mem_read_enable       <= 1'b0;
            decoded_mem_write_enable      <= 1'b0;
            decoded_nzp_write_enable      <= 1'b0;
            decoded_reg_input_selector    <= 2'b0;
            decoded_alu_arithmetic_selector <= 2'b0;
            decoded_alu_output_selector   <= 1'b0;
            decoded_pc_mux                <= 1'b0;
            decoded_ret                   <= 1'b0;
        end else begin
            if (core_state == DECODE) begin
                // --- Extract instruction fields ---
                // These are always pulled from the same bit positions regardless of opcode
                decoded_rd_address <= instruction[11:8];   // destination register
                decoded_rs_address <= instruction[7:4];    // source register 1
                decoded_rt_address <= instruction[3:0];    // source register 2
                decoded_immediate  <= instruction[7:0];    // immediate (overlaps rs/rt fields)
                decoded_nzp        <= instruction[11:9];   // NZP condition bits (overlaps rd field)

                // --- Default all control signals to 0 ---
                // Each instruction explicitly sets only the signals it needs.
                // Everything else stays 0 to avoid stale state from a previous instruction.
                decoded_reg_write_enable        <= 1'b0;
                decoded_mem_read_enable         <= 1'b0;
                decoded_mem_write_enable        <= 1'b0;
                decoded_nzp_write_enable        <= 1'b0;
                decoded_reg_input_selector      <= 2'b0;
                decoded_alu_arithmetic_selector <= 2'b0;
                decoded_alu_output_selector     <= 1'b0;
                decoded_pc_mux                  <= 1'b0;
                decoded_ret                     <= 1'b0;

                // --- Set control signals per opcode ---
                case (instruction[15:12])
                    NOP: begin
                        // No control signals needed - everything stays 0
                    end

                    BRnzp: begin
                        // Branch: next PC comes from immediate field, not increment
                        decoded_pc_mux <= 1'b1;
                    end

                    CMP: begin
                        // Compare: ALU runs in comparison mode, result updates NZP register
                        decoded_alu_output_selector <= 1'b1;
                        decoded_nzp_write_enable    <= 1'b1;
                    end

                    ADD: begin
                        decoded_reg_write_enable        <= 1'b1;
                        decoded_reg_input_selector      <= REG_SRC_ARITHMETIC;
                        decoded_alu_arithmetic_selector <= ALU_ADD;
                    end

                    SUB: begin
                        decoded_reg_write_enable        <= 1'b1;
                        decoded_reg_input_selector      <= REG_SRC_ARITHMETIC;
                        decoded_alu_arithmetic_selector <= ALU_SUB;
                    end

                    MUL: begin
                        decoded_reg_write_enable        <= 1'b1;
                        decoded_reg_input_selector      <= REG_SRC_ARITHMETIC;
                        decoded_alu_arithmetic_selector <= ALU_MUL;
                    end

                    DIV: begin
                        decoded_reg_write_enable        <= 1'b1;
                        decoded_reg_input_selector      <= REG_SRC_ARITHMETIC;
                        decoded_alu_arithmetic_selector <= ALU_DIV;
                    end

                    LDR: begin
                        // Load: read from memory, write result to rd
                        decoded_reg_write_enable   <= 1'b1;
                        decoded_reg_input_selector <= REG_SRC_MEMORY;
                        decoded_mem_read_enable    <= 1'b1;
                    end

                    STR: begin
                        // Store: write rt to memory address in rs (no register writeback)
                        decoded_mem_write_enable <= 1'b1;
                    end

                    CONST: begin
                        // Constant: load immediate value directly into rd
                        decoded_reg_write_enable   <= 1'b1;
                        decoded_reg_input_selector <= REG_SRC_CONSTANT;
                    end

                    RET: begin
                        // Return: signal that this thread is done
                        decoded_ret <= 1'b1;
                    end
                endcase
            end
        end
    end

endmodule

test/decoder_tb.sv
`default_nettype none
`timescale 1ns/1ns

module decoder_tb;
    reg         clock;
    reg         reset;
    reg  [2:0]  core_state;
    reg  [15:0] instruction;

    wire [3:0]  decoded_rd_address;
    wire [3:0]  decoded_rs_address;
    wire [3:0]  decoded_rt_address;
    wire [2:0]  decoded_nzp;
    wire [7:0]  decoded_immediate;
    wire        decoded_reg_write_enable;
    wire        decoded_mem_read_enable;
    wire        decoded_mem_write_enable;
    wire        decoded_nzp_write_enable;
    wire [1:0]  decoded_reg_input_selector;
    wire [1:0]  decoded_alu_arithmetic_selector;
    wire        decoded_alu_output_selector;
    wire        decoded_pc_mux;
    wire        decoded_ret;

    decoder uut (
        .clock                           (clock),
        .reset                           (reset),
        .core_state                      (core_state),
        .instruction                     (instruction),
        .decoded_rd_address              (decoded_rd_address),
        .decoded_rs_address              (decoded_rs_address),
        .decoded_rt_address              (decoded_rt_address),
        .decoded_nzp                     (decoded_nzp),
        .decoded_immediate               (decoded_immediate),
        .decoded_reg_write_enable        (decoded_reg_write_enable),
        .decoded_mem_read_enable         (decoded_mem_read_enable),
        .decoded_mem_write_enable        (decoded_mem_write_enable),
        .decoded_nzp_write_enable        (decoded_nzp_write_enable),
        .decoded_reg_input_selector      (decoded_reg_input_selector),
        .decoded_alu_arithmetic_selector (decoded_alu_arithmetic_selector),
        .decoded_alu_output_selector     (decoded_alu_output_selector),
        .decoded_pc_mux                  (decoded_pc_mux),
        .decoded_ret                     (decoded_ret)
    );

    // Clock generation: 10ns period (100MHz)
    always #5 clock = ~clock;

    // Pipeline stage
    localparam DECODE = 3'b010;

    // Opcodes
    localparam NOP   = 4'b0000;
    localparam BRnzp = 4'b0001;
    localparam CMP   = 4'b0010;
    localparam ADD   = 4'b0011;
    localparam SUB   = 4'b0100;
    localparam MUL   = 4'b0101;
    localparam DIV   = 4'b0110;
    localparam LDR   = 4'b0111;
    localparam STR   = 4'b1000;
    localparam CONST = 4'b1001;
    localparam RET   = 4'b1111;

    // Register input selector values
    localparam REG_SRC_ARITHMETIC = 2'b00;
    localparam REG_SRC_MEMORY     = 2'b01;
    localparam REG_SRC_CONSTANT   = 2'b10;

    // ALU arithmetic selector values
    localparam ALU_ADD = 2'b00;
    localparam ALU_SUB = 2'b01;
    localparam ALU_MUL = 2'b10;
    localparam ALU_DIV = 2'b11;

    integer tests_passed = 0;
    integer tests_failed = 0;

    task check_signal;
        input integer actual;
        input integer expected;
        input [255:0] label;
        begin
            if (actual === expected) begin
                $display("[PASS] %s", label);
                tests_passed = tests_passed + 1;
            end else begin
                $display("[FAIL] %s: expected %0d, got %0d", label, expected, actual);
                tests_failed = tests_failed + 1;
            end
        end
    endtask

    initial begin
        $dumpfile("decoder_tb.vcd");
        $dumpvars(0, decoder_tb);

        clock       = 0;
        reset       = 1;
        core_state  = 3'b000;
        instruction = 16'h0;

        $display("\n========================================");
        $display("Decoder Testbench Starting");
        $display("========================================\n");

        // Reset sequence
        #20;
        reset      = 0;
        core_state = DECODE;
        #10;

        // ==========================================
        // Test NOP
        // ==========================================
        $display("--- NOP ---\n");
        instruction = {NOP, 12'h0};
        #10;
        check_signal(decoded_reg_write_enable,        0, "NOP: reg_write_enable = 0");
        check_signal(decoded_mem_read_enable,         0, "NOP: mem_read_enable = 0");
        check_signal(decoded_mem_write_enable,        0, "NOP: mem_write_enable = 0");
        check_signal(decoded_nzp_write_enable,        0, "NOP: nzp_write_enable = 0");
        check_signal(decoded_alu_output_selector,     0, "NOP: alu_output_selector = 0");
        check_signal(decoded_pc_mux,                  0, "NOP: pc_mux = 0");
        check_signal(decoded_ret,                     0, "NOP: ret = 0");

        // ==========================================
        // Test ADD R3, R1, R2
        // ==========================================
        $display("\n--- ADD R3, R1, R2 ---\n");
        instruction = {ADD, 4'd3, 4'd1, 4'd2};
        #10;
        check_signal(decoded_rd_address,              3,                  "ADD: rd_address = 3");
        check_signal(decoded_rs_address,              1,                  "ADD: rs_address = 1");
        check_signal(decoded_rt_address,              2,                  "ADD: rt_address = 2");
        check_signal(decoded_reg_write_enable,        1,                  "ADD: reg_write_enable = 1");
        check_signal(decoded_reg_input_selector,      REG_SRC_ARITHMETIC, "ADD: reg_input_selector = ARITHMETIC");
        check_signal(decoded_alu_arithmetic_selector, ALU_ADD,            "ADD: alu_arithmetic_selector = ADD");
        check_signal(decoded_alu_output_selector,     0,                  "ADD: alu_output_selector = 0 (arithmetic)");
        check_signal(decoded_mem_read_enable,         0,                  "ADD: mem_read_enable = 0");
        check_signal(decoded_pc_mux,                  0,                  "ADD: pc_mux = 0");

        // ==========================================
        // Test SUB R5, R2, R4
        // ==========================================
        $display("\n--- SUB R5, R2, R4 ---\n");
        instruction = {SUB, 4'd5, 4'd2, 4'd4};
        #10;
        check_signal(decoded_alu_arithmetic_selector, ALU_SUB,            "SUB: alu_arithmetic_selector = SUB");
        check_signal(decoded_reg_write_enable,        1,                  "SUB: reg_write_enable = 1");
        check_signal(decoded_reg_input_selector,      REG_SRC_ARITHMETIC, "SUB: reg_input_selector = ARITHMETIC");

        // ==========================================
        // Test MUL R0, R7, R6
        // ==========================================
        $display("\n--- MUL R0, R7, R6 ---\n");
        instruction = {MUL, 4'd0, 4'd7, 4'd6};
        #10;
        check_signal(decoded_alu_arithmetic_selector, ALU_MUL,            "MUL: alu_arithmetic_selector = MUL");
        check_signal(decoded_reg_write_enable,        1,                  "MUL: reg_write_enable = 1");
        check_signal(decoded_reg_input_selector,      REG_SRC_ARITHMETIC, "MUL: reg_input_selector = ARITHMETIC");

        // ==========================================
        // Test DIV R1, R8, R9
        // ==========================================
        $display("\n--- DIV R1, R8, R9 ---\n");
        instruction = {DIV, 4'd1, 4'd8, 4'd9};
        #10;
        check_signal(decoded_alu_arithmetic_selector, ALU_DIV,            "DIV: alu_arithmetic_selector = DIV");
        check_signal(decoded_reg_write_enable,        1,                  "DIV: reg_write_enable = 1");
        check_signal(decoded_reg_input_selector,      REG_SRC_ARITHMETIC, "DIV: reg_input_selector = ARITHMETIC");

        // ==========================================
        // Test CMP R_, R2, R3
        // ==========================================
        $display("\n--- CMP ---\n");
        instruction = {CMP, 4'd0, 4'd2, 4'd3};
        #10;
        check_signal(decoded_alu_output_selector, 1, "CMP: alu_output_selector = 1 (comparison mode)");
        check_signal(decoded_nzp_write_enable,    1, "CMP: nzp_write_enable = 1");
        check_signal(decoded_reg_write_enable,    0, "CMP: reg_write_enable = 0 (no reg write)");

        // ==========================================
        // Test BRnzp  nzp=101, target=0x42
        // [15:12]=BRnzp, [11:9]=nzp, [8]=0, [7:0]=immediate
        // ==========================================
        $display("\n--- BRnzp (nzp=101, target=0x42) ---\n");
        instruction = {BRnzp, 3'b101, 1'b0, 8'h42};
        #10;
        check_signal(decoded_pc_mux,           1,      "BRnzp: pc_mux = 1 (branch)");
        check_signal(decoded_nzp,              3'b101, "BRnzp: nzp = 3'b101");
        check_signal(decoded_immediate,        8'h42,  "BRnzp: immediate = 0x42");
        check_signal(decoded_reg_write_enable, 0,      "BRnzp: reg_write_enable = 0");

        // ==========================================
        // Test LDR R4, R2
        // ==========================================
        $display("\n--- LDR R4, R2 ---\n");
        instruction = {LDR, 4'd4, 4'd2, 4'd0};
        #10;
        check_signal(decoded_reg_write_enable,   1,              "LDR: reg_write_enable = 1");
        check_signal(decoded_mem_read_enable,    1,              "LDR: mem_read_enable = 1");
        check_signal(decoded_reg_input_selector, REG_SRC_MEMORY, "LDR: reg_input_selector = MEMORY");
        check_signal(decoded_rd_address,         4,              "LDR: rd_address = 4");
        check_signal(decoded_rs_address,         2,              "LDR: rs_address = 2 (mem address)");
        check_signal(decoded_mem_write_enable,   0,              "LDR: mem_write_enable = 0");

        // ==========================================
        // Test STR rs=R2 (address), rt=R5 (data)
        // ==========================================
        $display("\n--- STR R2, R5 ---\n");
        instruction = {STR, 4'd0, 4'd2, 4'd5};
        #10;
        check_signal(decoded_mem_write_enable,  1, "STR: mem_write_enable = 1");
        check_signal(decoded_reg_write_enable,  0, "STR: reg_write_enable = 0 (no reg write)");
        check_signal(decoded_rs_address,        2, "STR: rs_address = 2 (address)");
        check_signal(decoded_rt_address,        5, "STR: rt_address = 5 (data)");
        check_signal(decoded_mem_read_enable,   0, "STR: mem_read_enable = 0");

        // ==========================================
        // Test CONST R6, #100
        // ==========================================
        $display("\n--- CONST R6, #100 ---\n");
        instruction = {CONST, 4'd6, 8'd100};
        #10;
        check_signal(decoded_reg_write_enable,   1,                 "CONST: reg_write_enable = 1");
        check_signal(decoded_reg_input_selector, REG_SRC_CONSTANT,  "CONST: reg_input_selector = CONSTANT");
        check_signal(decoded_rd_address,         6,                 "CONST: rd_address = 6");
        check_signal(decoded_immediate,          100,               "CONST: immediate = 100");
        check_signal(decoded_mem_read_enable,    0,                 "CONST: mem_read_enable = 0");

        // ==========================================
        // Test RET
        // ==========================================
        $display("\n--- RET ---\n");
        instruction = {RET, 12'h0};
        #10;
        check_signal(decoded_ret,              1, "RET: decoded_ret = 1");
        check_signal(decoded_reg_write_enable, 0, "RET: reg_write_enable = 0");
        check_signal(decoded_mem_read_enable,  0, "RET: mem_read_enable = 0");

        // ==========================================
        // Test: outputs hold outside DECODE stage
        // (last instruction was RET, decoded_ret = 1)
        // ==========================================
        $display("\n--- Hold outside DECODE stage ---\n");
        core_state  = 3'b000;
        instruction = {NOP, 12'h0};   // NOP presented but ignored (not DECODE)
        #10;
        check_signal(decoded_ret, 1, "Non-DECODE: outputs hold (ret still 1)");

        // Return to DECODE - NOP should clear ret
        core_state = DECODE;
        #10;
        check_signal(decoded_ret,              0, "Back to DECODE: NOP clears ret");
        check_signal(decoded_reg_write_enable, 0, "Back to DECODE: NOP clears reg_write_enable");

        // ==========================================
        // Test Reset
        // ==========================================
        $display("\n--- Reset ---\n");
        instruction = {ADD, 4'd3, 4'd1, 4'd2};
        core_state  = DECODE;
        #10;   // decode the ADD so signals are non-zero
        reset = 1;
        #10;
        check_signal(decoded_reg_write_enable, 0, "Reset: reg_write_enable = 0");
        check_signal(decoded_rd_address,       0, "Reset: rd_address = 0");
        check_signal(decoded_ret,              0, "Reset: ret = 0");
        check_signal(decoded_pc_mux,           0, "Reset: pc_mux = 0");
        reset = 0;

        // ==========================================
        // Summary
        // ==========================================
        #20;
        $display("\n========================================");
        $display("Test Summary");
        $display("========================================");
        $display("Passed: %d", tests_passed);
        $display("Failed: %d", tests_failed);
        $display("========================================\n");

        if (tests_failed == 0)
            $display("ALL TESTS PASSED!\n");
        else
            $display("SOME TESTS FAILED!\n");

        $finish;
    end

endmodule

test/decoder_tb.vcd
$date
	Sat Mar  7 20:28:13 2026
$end
$version
	Icarus Verilog
$end
$timescale
	1ns
$end
$scope module decoder_tb $end
$var wire 4 ! decoded_rt_address [3:0] $end
$var wire 4 " decoded_rs_address [3:0] $end
$var wire 1 # decoded_ret $end
$var wire 1 $ decoded_reg_write_enable $end
$var wire 2 % decoded_reg_input_selector [1:0] $end
$var wire 4 & decoded_rd_address [3:0] $end
$var wire 1 ' decoded_pc_mux $end
$var wire 1 ( decoded_nzp_write_enable $end
$var wire 3 ) decoded_nzp [2:0] $end
$var wire 1 * decoded_mem_write_enable $end
$var wire 1 + decoded_mem_read_enable $end
$var wire 8 , decoded_immediate [7:0] $end
$var wire 1 - decoded_alu_output_selector $end
$var wire 2 . decoded_alu_arithmetic_selector [1:0] $end
$var parameter 4 / ADD $end
$var parameter 2 0 ALU_ADD $end
$var parameter 2 1 ALU_DIV $end
$var parameter 2 2 ALU_MUL $end
$var parameter 2 3 ALU_SUB $end
$var parameter 4 4 BRnzp $end
$var parameter 4 5 CMP $end
$var parameter 4 6 CONST $end
$var parameter 3 7 DECODE $end
$var parameter 4 8 DIV $end
$var parameter 4 9 LDR $end
$var parameter 4 : MUL $end
$var parameter 4 ; NOP $end
$var parameter 2 < REG_SRC_ARITHMETIC $end
$var parameter 2 = REG_SRC_CONSTANT $end
$var parameter 2 > REG_SRC_MEMORY $end
$var parameter 4 ? RET $end
$var parameter 4 @ STR $end
$var parameter 4 A SUB $end
$var reg 1 B clock $end
$var reg 3 C core_state [2:0] $end
$var reg 16 D instruction [15:0] $end
$var reg 1 E reset $end
$var integer 32 F tests_failed [31:0] $end
$var integer 32 G tests_passed [31:0] $end
$scope module uut $end
$var wire 1 B clock $end
$var wire 3 H core_state [2:0] $end
$var wire 16 I instruction [15:0] $end
$var wire 1 E reset $end
$var parameter 4 J ADD $end
$var parameter 2 K ALU_ADD $end
$var parameter 2 L ALU_DIV $end
$var parameter 2 M ALU_MUL $end
$var parameter 2 N ALU_SUB $end
$var parameter 4 O BRnzp $end
$var parameter 4 P CMP $end
$var parameter 4 Q CONST $end
$var parameter 3 R DECODE $end
$var parameter 4 S DIV $end
$var parameter 4 T LDR $end
$var parameter 4 U MUL $end
$var parameter 4 V NOP $end
$var parameter 2 W REG_SRC_ARITHMETIC $end
$var parameter 2 X REG_SRC_CONSTANT $end
$var parameter 2 Y REG_SRC_MEMORY $end
$var parameter 4 Z RET $end
$var parameter 4 [ STR $end
$var parameter 4 \ SUB $end
$var reg 2 ] decoded_alu_arithmetic_selector [1:0] $end
$var reg 1 - decoded_alu_output_selector $end
$var reg 8 ^ decoded_immediate [7:0] $end
$var reg 1 + decoded_mem_read_enable $end
$var reg 1 * decoded_mem_write_enable $end
$var reg 3 _ decoded_nzp [2:0] $end
$var reg 1 ( decoded_nzp_write_enable $end
$var reg 1 ' decoded_pc_mux $end
$var reg 4 ` decoded_rd_address [3:0] $end
$var reg 2 a decoded_reg_input_selector [1:0] $end
$var reg 1 $ decoded_reg_write_enable $end
$var reg 1 # decoded_ret $end
$var reg 4 b decoded_rs_address [3:0] $end
$var reg 4 c decoded_rt_address [3:0] $end
$upscope $end
$scope task check_signal $end
$var reg 256 d label [255:0] $end
$var integer 32 e actual [31:0] $end
$var integer 32 f expected [31:0] $end
$upscope $end
$upscope $end
$enddefinitions $end
$comment Show the parameter values. $end
$dumpall
b100 \
b1000 [
b1111 Z
b1 Y
b10 X
b0 W
b0 V
b101 U
b111 T
b110 S
b10 R
b1001 Q
b10 P
b1 O
b1 N
b10 M
b11 L
b0 K
b11 J
b100 A
b1000 @
b1111 ?
b1 >
b10 =
b0 <
b0 ;
b101 :
b111 9
b110 8
b10 7
b1001 6
b10 5
b1 4
b1 3
b10 2
b11 1
b0 0
b11 /
$end
#0
$dumpvars
bx f
bx e
bx d
bx c
bx b
bx a
bx `
bx _
bx ^
bx ]
b0 I
b0 H
b0 G
b0 F
1E
b0 D
b0 C
0B
bx .
x-
bx ,
x+
x*
bx )
x(
x'
bx &
bx %
x$
x#
bx "
bx !
$end
#5
0#
0'
0-
b0 .
b0 ]
b0 %
b0 a
0(
0*
0+
0$
b0 ,
b0 ^
b0 )
b0 _
b0 !
b0 c
b0 "
b0 b
b0 &
b0 `
1B
#10
0B
#15
1B
#20
0B
b10 C
b10 H
0E
#25
1B
#30
0B
#35
1B
#40
0B
b11001100010010 D
b11001100010010 I
b111 G
b10011100100111101010000001110100010000001110010011001010111010000100000001111010010000000110000 d
b0 f
b0 e
#45
1$
b1 )
b1 _
b10010 ,
b10010 ^
b10 !
b10 c
b1 "
b1 b
b11 &
b11 `
1B
#50
0B
b100010100100100 D
b100010100100100 I
b10000 G
b10000010100010001000100001110100010000001110000011000110101111101101101011101010111100000100000001111010010000000110000 d
b0 f
b0 e
#55
b1 .
b1 ]
1$
b10 )
b10 _
b100100 ,
b100100 ^
b100 !
b100 c
b10 "
b10 b
b101 &
b101 `
1B
#60
0B
b101000001110110 D
b101000001110110 I
b10011 G
b10000001110010011001010110011101011111011010010110111001110000011101010111010001011111011100110110010101101100011001010110001101110100011011110111001000100000001111010010000001000001010100100100100101010100010010000100110101000101010101000100100101000011 d
b0 f
b0 e
#65
b10 .
b10 ]
1$
b0 )
b0 _
b1110110 ,
b1110110 ^
b110 !
b110 c
b111 "
b111 b
b0 &
b0 `
1B
#70
0B
b110000110001001 D
b110000110001001 I
b10110 G
b10000001110010011001010110011101011111011010010110111001110000011101010111010001011111011100110110010101101100011001010110001101110100011011110111001000100000001111010010000001000001010100100100100101010100010010000100110101000101010101000100100101000011 d
b0 f
b0 e
#75
b11 .
b11 ]
1$
b10001001 ,
b10001001 ^
b1001 !
b1001 c
b1000 "
b1000 b
b1 &
b1 `
1B
#80
0B
b10000000100011 D
b10000000100011 I
b11001 G
b10000001110010011001010110011101011111011010010110111001110000011101010111010001011111011100110110010101101100011001010110001101110100011011110111001000100000001111010010000001000001010100100100100101010100010010000100110101000101010101000100100101000011 d
b0 f
b0 e
#85
1(
1-
b0 .
b0 ]
0$
b100011 ,
b100011 ^
b11 !
b11 c
b10 "
b10 b
b0 &
b0 `
1B
#90
0B
b1101001000010 D
b1101001000010 I
b11100 G
b101111101110111011100100110100101110100011001010101111101100101011011100110000101100010011011000110010100100000001111010010000000110000001000000010100001101110011011110010000001110010011001010110011100100000011101110111001001101001011101000110010100101001 d
b0 f
b0 e
#95
1'
0-
0(
b101 )
b101 _
b1000010 ,
b1000010 ^
b10 !
b10 c
b100 "
b100 b
b1010 &
b1010 `
1B
#100
0B
b111010000100000 D
b111010000100000 I
b100000 G
b10000100101001001101110011110100111000000111010001000000111001001100101011001110101111101110111011100100110100101110100011001010101111101100101011011100110000101100010011011000110010100100000001111010010000000110000 d
b0 f
b0 e
#105
1+
b1 %
b1 a
1$
0'
b10 )
b10 _
b100000 ,
b100000 ^
b0 !
b0 c
b10 "
b10 b
b100 &
b100 `
1B
#110
0B
b1000000000100101 D
b1000000000100101 I
b100110 G
b1001100010001000101001000111010001000000110110101100101011011010101111101110111011100100110100101110100011001010101111101100101011011100110000101100010011011000110010100100000001111010010000000110000 d
b0 f
b0 e
#115
1*
b0 %
b0 a
0+
0$
b0 )
b0 _
b100101 ,
b100101 ^
b101 !
b101 c
b0 &
b0 `
1B
#120
0B
b1001011001100100 D
b1001011001100100 I
b101011 G
b10100110101010001010010001110100010000001101101011001010110110101011111011100100110010101100001011001000101111101100101011011100110000101100010011011000110010100100000001111010010000000110000 d
b0 f
b0 e
#125
b10 %
b10 a
1$
0*
b11 )
b11 _
b1100100 ,
b1100100 ^
b100 !
b100 c
b110 "
b110 b
b110 &
b110 `
1B
#130
0B
b1111000000000000 D
b1111000000000000 I
b110000 G
b100001101001111010011100101001101010100001110100010000001101101011001010110110101011111011100100110010101100001011001000101111101100101011011100110000101100010011011000110010100100000001111010010000000110000 d
b0 f
b0 e
#135
1#
b0 %
b0 a
0$
b0 )
b0 _
b0 ,
b0 ^
b0 !
b0 c
b0 "
b0 b
b0 &
b0 `
1B
#140
0B
b0 D
b0 I
b0 C
b0 H
b110011 G
b10100100100010101010100001110100010000001101101011001010110110101011111011100100110010101100001011001000101111101100101011011100110000101100010011011000110010100100000001111010010000000110000 d
b0 f
b0 e
#145
1B
#150
0B
b10 C
b10 H
b110100 G
b100001101001111010001000100010100111010001000000110111101110101011101000111000001110101011101000111001100100000011010000110111101101100011001000010000000101000011100100110010101110100001000000111001101110100011010010110110001101100001000000011000100101001 d
b1 f
b1 e
#155
0#
1B
#160
0B
b11001100010010 D
b11001100010010 I
b110110 G
b100111101000100010001010011101000100000010011100100111101010000001000000110001101101100011001010110000101110010011100110010000001110010011001010110011101011111011101110111001001101001011101000110010101011111011001010110111001100001011000100110110001100101 d
b0 f
b0 e
#165
1$
b1 )
b1 _
b10010 ,
b10010 ^
b10 !
b10 c
b1 "
b1 b
b11 &
b11 `
1B
#170
0B
1E
#175
0$
b0 ,
b0 ^
b0 )
b0 _
b0 !
b0 c
b0 "
b0 b
b0 &
b0 `
1B
#180
0B
0E
b111010 G
b101001001100101011100110110010101110100001110100010000001110000011000110101111101101101011101010111100000100000001111010010000000110000 d
#185
1$
b1 )
b1 _
b10010 ,
b10010 ^
b10 !
b10 c
b1 "
b1 b
b11 &
b11 `
1B
#190
0B
#195
1$
1B
