src/fetcher.sv
`default_nettype none
`timescale 1ns/1ns

// INSTRUCTION FETCHER
// > Runs in the FETCH stage - one fetcher shared across all threads in a core
// > Uses the current PC to request the next instruction from program memory
// > Issues an async read request, waits for the response, then latches the
//   16-bit instruction word so the decoder can pick it up in DECODE.
//
// Program-memory handshake (the same pattern the LSU and memory controller
// will reuse later):
//   1. Assert mem_read_valid with mem_read_address = current_pc
//   2. Hold until the controller answers with mem_read_ready
//   3. Latch mem_read_data into `instruction`, raise fetcher_done, drop valid
//
// One fetch per FETCH stage; fetcher_done tells the scheduler the instruction
// is ready so it can advance the core to DECODE.
module fetcher #(
    parameter PROGRAM_MEM_ADDR_BITS = 8,
    parameter PROGRAM_MEM_DATA_BITS = 16
) (
    input  wire clock,                                          // Heartbeat - all updates on rising edge
    input  wire reset,                                          // Force back to IDLE, clear outputs

    input  wire [2:0] core_state,                               // Which pipeline stage is the core in?

    // Program counter - address of the instruction we need to fetch
    input  wire [PROGRAM_MEM_ADDR_BITS-1:0] current_pc,

    // Program-memory read channel (we drive the request, controller answers)
    output reg                              mem_read_valid,     // We want to read...
    output reg  [PROGRAM_MEM_ADDR_BITS-1:0] mem_read_address,   // ...at this address
    input  wire                             mem_read_ready,     // Controller: your data is valid
    input  wire [PROGRAM_MEM_DATA_BITS-1:0] mem_read_data,      // ...here it is

    // Result handed to the decoder
    output reg                              fetcher_done,       // Instruction is latched and valid
    output reg  [PROGRAM_MEM_DATA_BITS-1:0] instruction         // The fetched 16-bit instruction word
);

    // ----- Core pipeline stages: canonical 3-bit encoding -----
    // Shared by every core module. The scheduler (built later) owns/drives these;
    // the codes already assumed by alu/decoder/registers/pc imply this layout.
    localparam IDLE    = 3'b000,
               FETCH   = 3'b001,
               DECODE  = 3'b010,
               REQUEST = 3'b011,
               WAIT    = 3'b100,
               EXECUTE = 3'b101,
               UPDATE  = 3'b110,
               DONE    = 3'b111;

    // ----- Fetcher's own little request state machine -----
    localparam FETCHER_IDLE     = 2'b00,   // Nothing in flight
               FETCHER_FETCHING = 2'b01,   // Request issued, waiting for ready
               FETCHER_DONE     = 2'b10;    // Instruction latched, holding result
    reg [1:0] fetcher_state;

    always @(posedge clock) begin
        if (reset) begin
            fetcher_state    <= FETCHER_IDLE;
            mem_read_valid   <= 1'b0;
            mem_read_address <= {PROGRAM_MEM_ADDR_BITS{1'b0}};
            fetcher_done     <= 1'b0;
            instruction      <= {PROGRAM_MEM_DATA_BITS{1'b0}};
        end else begin
            case (fetcher_state)
                FETCHER_IDLE: begin
                    // Wait until the core enters the FETCH stage, then fire a
                    // read request for the instruction at the current PC.
                    if (core_state == FETCH) begin
                        fetcher_state    <= FETCHER_FETCHING;
                        mem_read_valid   <= 1'b1;
                        mem_read_address <= current_pc;
                    end
                end

                FETCHER_FETCHING: begin
                    // Request is in flight - wait for the controller to answer.
                    if (mem_read_ready) begin
                        fetcher_state  <= FETCHER_DONE;
                        mem_read_valid <= 1'b0;             // drop the request
                        instruction    <= mem_read_data;    // latch the result
                        fetcher_done   <= 1'b1;             // tell the scheduler
                    end
                end

                FETCHER_DONE: begin
                    // Hold the instruction + done flag until the scheduler moves
                    // the core out of FETCH (into DECODE), then arm for next time.
                    if (core_state != FETCH) begin
                        fetcher_state <= FETCHER_IDLE;
                        fetcher_done  <= 1'b0;
                    end
                end

                default: begin
                    fetcher_state <= FETCHER_IDLE;
                end
            endcase
        end
    end

endmodule

test/fetcher_tb.sv
`default_nettype none
`timescale 1ns/1ns

// FETCHER TESTBENCH
// Drives the fetcher with a mock program memory that answers the
// valid -> ready handshake after a configurable latency, and checks that the
// correct instruction word comes back for the requested PC.
module fetcher_tb;
    reg        clock;
    reg        reset;
    reg  [2:0] core_state;
    reg  [7:0] current_pc;

    // Program-memory read channel (driven by the fetcher, answered by the mock)
    wire        mem_read_valid;
    wire [7:0]  mem_read_address;
    reg         mem_read_ready;
    reg  [15:0] mem_read_data;

    // Results out of the fetcher
    wire        fetcher_done;
    wire [15:0] instruction;

    fetcher #(
        .PROGRAM_MEM_ADDR_BITS (8),
        .PROGRAM_MEM_DATA_BITS (16)
    ) uut (
        .clock            (clock),
        .reset            (reset),
        .core_state       (core_state),
        .current_pc       (current_pc),
        .mem_read_valid   (mem_read_valid),
        .mem_read_address (mem_read_address),
        .mem_read_ready   (mem_read_ready),
        .mem_read_data    (mem_read_data),
        .fetcher_done     (fetcher_done),
        .instruction      (instruction)
    );

    // Clock generation: 10ns period (100MHz)
    always #5 clock = ~clock;

    // Pipeline stages (must match the encoding in fetcher.sv)
    localparam FETCH  = 3'b001;
    localparam DECODE = 3'b010;

    // ----- Mock program memory -----
    reg [15:0] prog_mem [0:255];
    integer    mem_latency   = 1;   // cycles before the memory answers a request
    integer    mem_wait_cnt  = 0;

    always @(posedge clock) begin
        if (reset) begin
            mem_read_ready <= 1'b0;
            mem_read_data  <= 16'b0;
            mem_wait_cnt   <= 0;
        end else if (mem_read_valid && !mem_read_ready) begin
            // Request in flight: count down the latency, then answer for one cycle
            if (mem_wait_cnt >= mem_latency) begin
                mem_read_ready <= 1'b1;
                mem_read_data  <= prog_mem[mem_read_address];
                mem_wait_cnt   <= 0;
            end else begin
                mem_wait_cnt <= mem_wait_cnt + 1;
            end
        end else begin
            mem_read_ready <= 1'b0;
            mem_wait_cnt   <= 0;
        end
    end

    integer tests_passed = 0;
    integer tests_failed = 0;

    task check_signal;
        input integer actual;
        input integer expected;
        input [255:0] label;
        begin
            if (actual === expected) begin
                $display("[PASS] %s", label);
                tests_passed = tests_passed + 1;
            end else begin
                $display("[FAIL] %s: expected %0d, got %0d", label, expected, actual);
                tests_failed = tests_failed + 1;
            end
        end
    endtask

    // Enter FETCH at `addr` and block until the fetcher reports done.
    // (instruction + fetcher_done are held valid on return, before re-arming.)
    task start_fetch;
        input [7:0] addr;
        integer guard;
        begin
            current_pc = addr;
            core_state = FETCH;
            guard = 0;
            while (fetcher_done !== 1'b1 && guard < 100) begin
                #10;
                guard = guard + 1;
            end
        end
    endtask

    // Advance the core out of FETCH so the fetcher re-arms for the next request.
    task end_fetch;
        begin
            core_state = DECODE;
            #10;
        end
    endtask

    initial begin
        $dumpfile("fetcher_tb.vcd");
        $dumpvars(0, fetcher_tb);

        // Preload the mock program memory with a few recognizable words
        prog_mem[0]  = 16'h3120;   // ADD   R1, R2, R0
        prog_mem[1]  = 16'h9105;   // CONST R1, 5
        prog_mem[2]  = 16'h0000;   // NOP
        prog_mem[3]  = 16'hF000;   // RET
        prog_mem[42] = 16'hABCD;   // arbitrary, for a non-sequential fetch

        clock          = 0;
        reset          = 1;
        core_state     = DECODE;   // start parked outside FETCH
        current_pc     = 8'd0;
        mem_read_ready = 0;
        mem_read_data  = 0;

        $display("\n========================================");
        $display("Fetcher Testbench Starting");
        $display("========================================\n");

        // Reset sequence
        #20;
        check_signal(fetcher_done,   0, "Reset: fetcher_done = 0");
        check_signal(mem_read_valid, 0, "Reset: mem_read_valid = 0");
        check_signal(instruction,    0, "Reset: instruction = 0");

        reset = 0;
        #10;

        // ==========================================
        // Basic fetch
        // ==========================================
        $display("\n--- Basic fetch ---\n");

        start_fetch(8'd0);
        check_signal(instruction,    prog_mem[0], "Fetch @0 -> prog_mem[0] (0x3120)");
        check_signal(fetcher_done,   1,           "Fetch @0: fetcher_done asserted");
        check_signal(mem_read_valid, 0,           "Fetch @0: valid dropped after handshake");
        end_fetch();
        check_signal(fetcher_done,   0,           "done clears after leaving FETCH (re-arm)");

        // ==========================================
        // Sequential fetches
        // ==========================================
        $display("\n--- Sequential fetches ---\n");

        start_fetch(8'd1);
        check_signal(instruction, prog_mem[1], "Fetch @1 -> CONST (0x9105)");
        end_fetch();

        start_fetch(8'd2);
        check_signal(instruction, prog_mem[2], "Fetch @2 -> NOP (0x0000)");
        end_fetch();

        start_fetch(8'd3);
        check_signal(instruction, prog_mem[3], "Fetch @3 -> RET (0xF000)");
        end_fetch();

        // ==========================================
        // Non-sequential address
        // ==========================================
        $display("\n--- Non-sequential address ---\n");

        start_fetch(8'd42);
        check_signal(instruction, prog_mem[42], "Fetch @42 -> 0xABCD");
        end_fetch();

        // ==========================================
        // Slow memory: fetcher must wait for ready
        // ==========================================
        $display("\n--- Slow memory (high latency) ---\n");

        mem_latency = 5;
        start_fetch(8'd1);
        check_signal(instruction,  prog_mem[1], "Slow fetch @1 still returns 0x9105");
        check_signal(fetcher_done, 1,           "Slow fetch: done eventually asserted");
        end_fetch();
        mem_latency = 1;

        // ==========================================
        // Reset mid-life clears outputs
        // ==========================================
        $display("\n--- Reset clears state ---\n");

        reset = 1;
        #10;
        check_signal(fetcher_done,   0, "Reset: fetcher_done = 0");
        check_signal(mem_read_valid, 0, "Reset: mem_read_valid = 0");
        check_signal(instruction,    0, "Reset: instruction = 0");
        reset = 0;
        #10;

        // Fetch works again after reset
        start_fetch(8'd0);
        check_signal(instruction, prog_mem[0], "Post-reset fetch @0 -> 0x3120");
        end_fetch();

        // ==========================================
        // Summary
        // ==========================================
        #20;
        $display("\n========================================");
        $display("Test Summary");
        $display("========================================");
        $display("Passed: %d", tests_passed);
        $display("Failed: %d", tests_failed);
        $display("========================================\n");

        if (tests_failed == 0)
            $display("ALL TESTS PASSED!\n");
        else
            $display("SOME TESTS FAILED!\n");

        $finish;
    end

endmodule

test/fetcher_tb.vcd
$date
	Fri Jun  5 11:08:43 2026
$end
$version
	Icarus Verilog
$end
$timescale
	1ns
$end
$scope module fetcher_tb $end
$var wire 1 ! mem_read_valid $end
$var wire 8 " mem_read_address [7:0] $end
$var wire 16 # instruction [15:0] $end
$var wire 1 $ fetcher_done $end
$var parameter 3 % DECODE $end
$var parameter 3 & FETCH $end
$var reg 1 ' clock $end
$var reg 3 ( core_state [2:0] $end
$var reg 8 ) current_pc [7:0] $end
$var reg 16 * mem_read_data [15:0] $end
$var reg 1 + mem_read_ready $end
$var reg 1 , reset $end
$var integer 32 - mem_latency [31:0] $end
$var integer 32 . mem_wait_cnt [31:0] $end
$var integer 32 / tests_failed [31:0] $end
$var integer 32 0 tests_passed [31:0] $end
$scope module uut $end
$var wire 1 ' clock $end
$var wire 3 1 core_state [2:0] $end
$var wire 8 2 current_pc [7:0] $end
$var wire 16 3 mem_read_data [15:0] $end
$var wire 1 + mem_read_ready $end
$var wire 1 , reset $end
$var parameter 3 4 DECODE $end
$var parameter 3 5 DONE $end
$var parameter 3 6 EXECUTE $end
$var parameter 3 7 FETCH $end
$var parameter 2 8 FETCHER_DONE $end
$var parameter 2 9 FETCHER_FETCHING $end
$var parameter 2 : FETCHER_IDLE $end
$var parameter 3 ; IDLE $end
$var parameter 32 < PROGRAM_MEM_ADDR_BITS $end
$var parameter 32 = PROGRAM_MEM_DATA_BITS $end
$var parameter 3 > REQUEST $end
$var parameter 3 ? UPDATE $end
$var parameter 3 @ WAIT $end
$var reg 1 $ fetcher_done $end
$var reg 2 A fetcher_state [1:0] $end
$var reg 16 B instruction [15:0] $end
$var reg 8 C mem_read_address [7:0] $end
$var reg 1 ! mem_read_valid $end
$upscope $end
$scope task check_signal $end
$var reg 256 D label [255:0] $end
$var integer 32 E actual [31:0] $end
$var integer 32 F expected [31:0] $end
$upscope $end
$scope task end_fetch $end
$upscope $end
$scope task start_fetch $end
$var reg 8 G addr [7:0] $end
$var integer 32 H guard [31:0] $end
$upscope $end
$upscope $end
$enddefinitions $end
$comment Show the parameter values. $end
$dumpall
b100 @
b110 ?
b11 >
b10000 =
b1000 <
b0 ;
b0 :
b1 9
b10 8
b1 7
b101 6
b111 5
b10 4
b1 &
b10 %
$end
#0
$dumpvars
bx H
bx G
bx F
bx E
bx D
bx C
bx B
bx A
b0 3
b0 2
b10 1
b0 0
b0 /
b0 .
b1 -
1,
0+
b0 *
b0 )
b10 (
0'
x$
bx #
bx "
x!
$end
#5
b0 #
b0 B
0$
b0 "
b0 C
0!
b0 A
1'
#10
0'
#15
1'
#20
0'
0,
b11 0
b1010010011001010111001101100101011101000011101000100000011010010110111001110011011101000111001001110101011000110111010001101001011011110110111000100000001111010010000000110000 D
b0 F
b0 E
#25
1'
#30
0'
b0 H
b1 (
b1 1
b0 G
#35
1!
b1 A
1'
#40
0'
b1 H
#45
b1 .
1'
#50
0'
b10 H
#55
b0 .
b11000100100000 *
b11000100100000 3
1+
1'
#60
0'
b11 H
#65
1$
b11000100100000 #
b11000100100000 B
0!
b10 A
0+
1'
#70
0'
b10 (
b10 1
b110 0
b11000000111010001000000111011001100001011011000110100101100100001000000110010001110010011011110111000001110000011001010110010000100000011000010110011001110100011001010111001000100000011010000110000101101110011001000111001101101000011000010110101101100101 D
b0 F
b0 E
b100 H
#75
0$
b0 A
1'
#80
0'
b0 H
b1 (
b1 1
b1 )
b1 2
b1 G
b111 0
b110000101110010011100110010000001100001011001100111010001100101011100100010000001101100011001010110000101110110011010010110111001100111001000000100011001000101010101000100001101001000001000000010100001110010011001010010110101100001011100100110110100101001 D
#85
b1 "
b1 C
1!
b1 A
1'
#90
0'
b1 H
#95
b1 .
1'
#100
0'
b10 H
#105
b0 .
b1001000100000101 *
b1001000100000101 3
1+
1'
#110
0'
b11 H
#115
0+
1$
b1001000100000101 #
b1001000100000101 B
0!
b10 A
1'
#120
0'
b10 (
b10 1
b1000 0
b100011001100101011101000110001101101000001000000100000000110001001000000010110100111110001000000100001101001111010011100101001101010100001000000010100000110000011110000011100100110001001100000011010100101001 D
b1001000100000101 F
b1001000100000101 E
b100 H
#125
0$
b0 A
1'
#130
0'
b0 H
b1 (
b1 1
b10 )
b10 2
b10 G
#135
b10 "
b10 C
1!
b1 A
1'
#140
0'
b1 H
#145
b1 .
1'
#150
0'
b10 H
#155
b0 .
b0 *
b0 3
1+
1'
#160
0'
b11 H
#165
1$
b0 #
b0 B
0!
b10 A
0+
1'
#170
0'
b10 (
b10 1
b1001 0
b10001100110010101110100011000110110100000100000010000000011001000100000001011010011111000100000010011100100111101010000001000000010100000110000011110000011000000110000001100000011000000101001 D
b0 F
b0 E
b100 H
#175
0$
b0 A
1'
#180
0'
b0 H
b1 (
b1 1
b11 )
b11 2
b11 G
#185
b11 "
b11 C
1!
b1 A
1'
#190
0'
b1 H
#195
b1 .
1'
#200
0'
b10 H
#205
b0 .
b1111000000000000 *
b1111000000000000 3
1+
1'
#210
0'
b11 H
#215
0+
1$
b1111000000000000 #
b1111000000000000 B
0!
b10 A
1'
#220
0'
b10 (
b10 1
b1010 0
b10001100110010101110100011000110110100000100000010000000011001100100000001011010011111000100000010100100100010101010100001000000010100000110000011110000100011000110000001100000011000000101001 D
b1111000000000000 F
b1111000000000000 E
b100 H
#225
0$
b0 A
1'
#230
0'
b0 H
b1 (
b1 1
b101010 )
b101010 2
b101010 G
#235
b101010 "
b101010 C
1!
b1 A
1'
#240
0'
b1 H
#245
b1 .
1'
#250
0'
b10 H
#255
b0 .
b1010101111001101 *
b1010101111001101 3
1+
1'
#260
0'
b11 H
#265
1$
b1010101111001101 #
b1010101111001101 B
0!
b10 A
0+
1'
#270
0'
b10 (
b10 1
b1011 0
b1000110011001010111010001100011011010000010000001000000001101000011001000100000001011010011111000100000001100000111100001000001010000100100001101000100 D
b1010101111001101 F
b1010101111001101 E
b100 H
#275
0$
b0 A
1'
#280
0'
b0 H
b1 (
b1 1
b1 )
b1 2
b1 G
b101 -
#285
b1 "
b1 C
1!
b1 A
1'
#290
0'
b1 H
#295
b1 .
1'
#300
0'
b10 H
#305
b10 .
1'
#310
0'
b11 H
#315
b11 .
1'
#320
0'
b100 H
#325
b100 .
1'
#330
0'
b101 H
#335
b101 .
1'
#340
0'
b110 H
#345
b0 .
b1001000100000101 *
b1001000100000101 3
1+
1'
#350
0'
b111 H
#355
0+
1$
b1001000100000101 #
b1001000100000101 B
0!
b10 A
1'
#360
0'
b10 (
b10 1
b1101 0
b10000001100110011001010111010001100011011010000011101000100000011001000110111101101110011001010010000001100101011101100110010101101110011101000111010101100001011011000110110001111001001000000110000101110011011100110110010101110010011101000110010101100100 D
b1 F
b1 E
b1000 H
#365
0$
b0 A
1'
#370
0'
1,
b1 -
#375
b0 *
b0 3
b0 #
b0 B
b0 "
b0 C
1'
#380
0'
0,
b10000 0
b1010010011001010111001101100101011101000011101000100000011010010110111001110011011101000111001001110101011000110111010001101001011011110110111000100000001111010010000000110000 D
b0 F
b0 E
#385
1'
#390
0'
b0 H
b1 (
b1 1
b0 )
b0 2
b0 G
#395
1!
b1 A
1'
#400
0'
b1 H
#405
b1 .
1'
#410
0'
b10 H
#415
b0 .
b11000100100000 *
b11000100100000 3
1+
1'
#420
0'
b11 H
#425
1$
b11000100100000 #
b11000100100000 B
0!
b10 A
0+
1'
#430
0'
b10 (
b10 1
b10001 0
b101000001101111011100110111010000101101011100100110010101110011011001010111010000100000011001100110010101110100011000110110100000100000010000000011000000100000001011010011111000100000001100000111100000110011001100010011001000110000 D
b11000100100000 F
b11000100100000 E
b100 H
#435
0$
b0 A
1'
