src/lsu.sv
`default_nettype none
`timescale 1ns/1ns

// LOAD / STORE UNIT
// One LSU per thread (hence `enable` for SIMT masking). Handles the two memory
// instructions, LDR and STR, by talking to data memory over a valid -> ready
// handshake - the same pattern the fetcher uses for program memory.
//
//   LDR rd, [rs]  -> read  data_mem[rs], result appears on lsu_out (-> regfile)
//   STR [rs], rt  -> write data_mem[rs] = rt
//
// Lifecycle across the pipeline:
//   REQUEST stage : kick off (move IDLE -> REQUESTING)
//   (internal)    : drive the request, then wait for ready
//   UPDATE  stage : retire (move DONE -> IDLE) once the result has been consumed
module lsu (
    input  wire clock,                          // Heartbeat
    input  wire reset,                          // Force back to IDLE, clear outputs
    input  wire enable,                         // Is this thread active? (SIMT masking)

    input  wire [2:0] core_state,               // Which pipeline stage is the core in?

    // Decoded control signals (mutually exclusive for memory ops)
    input  wire decoded_mem_read_enable,        // LDR: read from memory
    input  wire decoded_mem_write_enable,       // STR: write to memory

    // Operands from the register file
    input  wire [7:0] rs,                       // Memory address
    input  wire [7:0] rt,                       // Data to store (STR only)

    // Data-memory read channel (we drive the request, controller answers)
    output reg        mem_read_valid,
    output reg [7:0]  mem_read_address,
    input  wire       mem_read_ready,
    input  wire [7:0] mem_read_data,

    // Data-memory write channel
    output reg        mem_write_valid,
    output reg [7:0]  mem_write_address,
    output reg [7:0]  mem_write_data,
    input  wire       mem_write_ready,

    // Result handed back to the register file (LDR)
    output reg [7:0]  lsu_out,

    // Exposed so the scheduler can stall in WAIT until memory traffic settles
    output reg [1:0]  lsu_state
);

    // Core pipeline stages we care about (canonical encoding)
    localparam REQUEST = 3'b011;    // Kick off the memory transaction
    localparam UPDATE  = 3'b110;    // Transaction retires here

    // LSU's own transaction state machine
    localparam LSU_IDLE       = 2'b00,   // Nothing in flight
               LSU_REQUESTING = 2'b01,   // Drive the request onto the bus
               LSU_WAITING    = 2'b10,   // Request issued, waiting for ready
               LSU_DONE       = 2'b11;   // Transaction complete, holding result

    always @(posedge clock) begin
        if (reset) begin
            lsu_state         <= LSU_IDLE;
            mem_read_valid    <= 1'b0;
            mem_read_address  <= 8'b0;
            mem_write_valid   <= 1'b0;
            mem_write_address <= 8'b0;
            mem_write_data    <= 8'b0;
            lsu_out           <= 8'b0;
        end else if (enable) begin
            // Only LDR/STR drive the LSU; every other instruction leaves it idle.
            if (decoded_mem_read_enable || decoded_mem_write_enable) begin
                case (lsu_state)
                    LSU_IDLE: begin
                        // Arm once the core reaches the REQUEST stage
                        if (core_state == REQUEST) begin
                            lsu_state <= LSU_REQUESTING;
                        end
                    end

                    LSU_REQUESTING: begin
                        // Put the request on the appropriate channel
                        if (decoded_mem_read_enable) begin
                            mem_read_valid   <= 1'b1;
                            mem_read_address <= rs;
                        end else begin
                            mem_write_valid   <= 1'b1;
                            mem_write_address <= rs;
                            mem_write_data    <= rt;
                        end
                        lsu_state <= LSU_WAITING;
                    end

                    LSU_WAITING: begin
                        // Wait for the controller to acknowledge
                        if (decoded_mem_read_enable && mem_read_ready) begin
                            mem_read_valid <= 1'b0;            // drop the request
                            lsu_out        <= mem_read_data;   // latch the loaded value
                            lsu_state      <= LSU_DONE;
                        end else if (decoded_mem_write_enable && mem_write_ready) begin
                            mem_write_valid <= 1'b0;           // drop the request
                            lsu_state       <= LSU_DONE;
                        end
                    end

                    LSU_DONE: begin
                        // Retire once the result has been consumed in UPDATE
                        if (core_state == UPDATE) begin
                            lsu_state <= LSU_IDLE;
                        end
                    end
                endcase
            end
        end
    end

endmodule

test/lsu_tb.sv
`default_nettype none
`timescale 1ns/1ns

// LSU TESTBENCH
// Drives the load/store unit with a mock data memory (separate read and write
// channels, each with a configurable latency) and checks that LDR returns the
// stored value and STR writes the right data to the right address.
module lsu_tb;
    reg        clock;
    reg        reset;
    reg        enable;
    reg  [2:0] core_state;
    reg        decoded_mem_read_enable;
    reg        decoded_mem_write_enable;
    reg  [7:0] rs;
    reg  [7:0] rt;

    // Read channel (LSU drives request, mock answers)
    wire        mem_read_valid;
    wire [7:0]  mem_read_address;
    reg         mem_read_ready;
    reg  [7:0]  mem_read_data;

    // Write channel
    wire        mem_write_valid;
    wire [7:0]  mem_write_address;
    wire [7:0]  mem_write_data;
    reg         mem_write_ready;

    wire [7:0]  lsu_out;

    lsu uut (
        .clock                    (clock),
        .reset                    (reset),
        .enable                   (enable),
        .core_state               (core_state),
        .decoded_mem_read_enable  (decoded_mem_read_enable),
        .decoded_mem_write_enable (decoded_mem_write_enable),
        .rs                       (rs),
        .rt                       (rt),
        .mem_read_valid           (mem_read_valid),
        .mem_read_address         (mem_read_address),
        .mem_read_ready           (mem_read_ready),
        .mem_read_data            (mem_read_data),
        .mem_write_valid          (mem_write_valid),
        .mem_write_address        (mem_write_address),
        .mem_write_data           (mem_write_data),
        .mem_write_ready          (mem_write_ready),
        .lsu_out                  (lsu_out)
    );

    // Clock generation: 10ns period
    always #5 clock = ~clock;

    // Pipeline stages (must match lsu.sv)
    localparam DECODE  = 3'b010;
    localparam REQUEST = 3'b011;
    localparam UPDATE  = 3'b110;

    // ----- Mock data memory -----
    reg [7:0] data_mem [0:255];

    integer rd_latency = 1;
    integer rd_cnt     = 0;
    always @(posedge clock) begin
        if (reset) begin
            mem_read_ready <= 1'b0;
            mem_read_data  <= 8'b0;
            rd_cnt         <= 0;
        end else if (mem_read_valid && !mem_read_ready) begin
            if (rd_cnt >= rd_latency) begin
                mem_read_ready <= 1'b1;
                mem_read_data  <= data_mem[mem_read_address];
                rd_cnt         <= 0;
            end else begin
                rd_cnt <= rd_cnt + 1;
            end
        end else begin
            mem_read_ready <= 1'b0;
            rd_cnt         <= 0;
        end
    end

    integer wr_latency = 1;
    integer wr_cnt     = 0;
    always @(posedge clock) begin
        if (reset) begin
            mem_write_ready <= 1'b0;
            wr_cnt          <= 0;
        end else if (mem_write_valid && !mem_write_ready) begin
            if (wr_cnt >= wr_latency) begin
                mem_write_ready              <= 1'b1;
                data_mem[mem_write_address]  <= mem_write_data;
                wr_cnt                       <= 0;
            end else begin
                wr_cnt <= wr_cnt + 1;
            end
        end else begin
            mem_write_ready <= 1'b0;
            wr_cnt          <= 0;
        end
    end

    integer tests_passed = 0;
    integer tests_failed = 0;

    task check_signal;
        input integer actual;
        input integer expected;
        input [255:0] label;
        begin
            if (actual === expected) begin
                $display("[PASS] %s", label);
                tests_passed = tests_passed + 1;
            end else begin
                $display("[FAIL] %s: expected %0d, got %0d", label, expected, actual);
                tests_failed = tests_failed + 1;
            end
        end
    endtask

    // Run a LDR: REQUEST -> wait for the read handshake -> retire in UPDATE.
    task do_load;
        input [7:0] addr;
        integer guard;
        reg     seen;
        begin
            decoded_mem_read_enable  = 1;
            decoded_mem_write_enable = 0;
            rs = addr;
            core_state = REQUEST;
            seen = 0; guard = 0;
            while (!(seen && mem_read_valid === 1'b0) && guard < 50) begin
                if (mem_read_valid === 1'b1) seen = 1;
                #10; guard = guard + 1;
            end
            core_state = UPDATE; #10;           // retire (DONE -> IDLE)
            decoded_mem_read_enable = 0;
            core_state = DECODE; #10;           // park outside the memory stages
        end
    endtask

    // Run a STR: REQUEST -> wait for the write handshake -> retire in UPDATE.
    task do_store;
        input [7:0] addr;
        input [7:0] val;
        integer guard;
        reg     seen;
        begin
            decoded_mem_read_enable  = 0;
            decoded_mem_write_enable = 1;
            rs = addr;
            rt = val;
            core_state = REQUEST;
            seen = 0; guard = 0;
            while (!(seen && mem_write_valid === 1'b0) && guard < 50) begin
                if (mem_write_valid === 1'b1) seen = 1;
                #10; guard = guard + 1;
            end
            core_state = UPDATE; #10;
            decoded_mem_write_enable = 0;
            core_state = DECODE; #10;
        end
    endtask

    initial begin
        $dumpfile("lsu_tb.vcd");
        $dumpvars(0, lsu_tb);

        // Preload data memory
        data_mem[8'h10] = 8'h42;
        data_mem[8'h11] = 8'h07;
        data_mem[8'h80] = 8'hFE;

        clock                    = 0;
        reset                    = 1;
        enable                   = 0;
        core_state               = DECODE;
        decoded_mem_read_enable  = 0;
        decoded_mem_write_enable = 0;
        rs                       = 0;
        rt                       = 0;
        mem_read_ready           = 0;
        mem_read_data            = 0;
        mem_write_ready          = 0;

        $display("\n========================================");
        $display("LSU Testbench Starting");
        $display("========================================\n");

        // Reset sequence
        #20;
        check_signal(lsu_out,         0, "Reset: lsu_out = 0");
        check_signal(mem_read_valid,  0, "Reset: mem_read_valid = 0");
        check_signal(mem_write_valid, 0, "Reset: mem_write_valid = 0");

        reset  = 0;
        enable = 1;
        #10;

        // ==========================================
        // LDR
        // ==========================================
        $display("\n--- LDR (load) ---\n");

        do_load(8'h10);
        check_signal(lsu_out,        8'h42, "LDR [0x10] -> lsu_out = 0x42");
        check_signal(mem_read_valid, 0,     "LDR: read request deasserted");

        do_load(8'h11);
        check_signal(lsu_out, 8'h07, "LDR [0x11] -> lsu_out = 0x07");

        do_load(8'h80);
        check_signal(lsu_out, 8'hFE, "LDR [0x80] -> lsu_out = 0xFE");

        // ==========================================
        // STR
        // ==========================================
        $display("\n--- STR (store) ---\n");

        do_store(8'h20, 8'h99);
        check_signal(data_mem[8'h20],  8'h99, "STR 0x99 -> [0x20] writes memory");
        check_signal(mem_write_valid,  0,     "STR: write request deasserted");

        do_store(8'h21, 8'hAB);
        check_signal(data_mem[8'h21], 8'hAB, "STR 0xAB -> [0x21]");

        // Load back what we just stored
        do_load(8'h20);
        check_signal(lsu_out, 8'h99, "LDR [0x20] reads back 0x99 (store/load round-trip)");

        // ==========================================
        // Slow memory: LSU must wait for ready
        // ==========================================
        $display("\n--- Slow memory ---\n");

        rd_latency = 5;
        do_load(8'h11);
        check_signal(lsu_out, 8'h07, "Slow LDR [0x11] still returns 0x07");
        rd_latency = 1;

        // ==========================================
        // Enable masking: disabled thread issues nothing
        // ==========================================
        $display("\n--- Enable masking ---\n");

        enable                  = 0;
        decoded_mem_read_enable = 1;
        rs                      = 8'h80;     // would load 0xFE if active
        core_state              = REQUEST;
        #50;
        check_signal(mem_read_valid, 0,     "Disabled: no read request issued");
        check_signal(lsu_out,        8'h07, "Disabled: lsu_out unchanged (still 0x07)");
        decoded_mem_read_enable = 0;
        core_state              = DECODE;
        enable                  = 1;
        #10;

        // Works again once re-enabled
        do_load(8'h80);
        check_signal(lsu_out, 8'hFE, "Re-enabled: LDR [0x80] -> 0xFE");

        // ==========================================
        // Reset clears state
        // ==========================================
        $display("\n--- Reset clears state ---\n");

        reset = 1;
        #10;
        check_signal(lsu_out,         0, "Reset: lsu_out = 0");
        check_signal(mem_read_valid,  0, "Reset: mem_read_valid = 0");
        check_signal(mem_write_valid, 0, "Reset: mem_write_valid = 0");
        reset = 0;
        #10;

        // ==========================================
        // Summary
        // ==========================================
        #20;
        $display("\n========================================");
        $display("Test Summary");
        $display("========================================");
        $display("Passed: %d", tests_passed);
        $display("Failed: %d", tests_failed);
        $display("========================================\n");

        if (tests_failed == 0)
            $display("ALL TESTS PASSED!\n");
        else
            $display("SOME TESTS FAILED!\n");

        $finish;
    end

endmodule

test/lsu_tb.vcd
$date
	Fri Jun  5 11:08:43 2026
$end
$version
	Icarus Verilog
$end
$timescale
	1ns
$end
$scope module lsu_tb $end
$var wire 1 ! mem_write_valid $end
$var wire 8 " mem_write_data [7:0] $end
$var wire 8 # mem_write_address [7:0] $end
$var wire 1 $ mem_read_valid $end
$var wire 8 % mem_read_address [7:0] $end
$var wire 8 & lsu_out [7:0] $end
$var parameter 3 ' DECODE $end
$var parameter 3 ( REQUEST $end
$var parameter 3 ) UPDATE $end
$var reg 1 * clock $end
$var reg 3 + core_state [2:0] $end
$var reg 1 , decoded_mem_read_enable $end
$var reg 1 - decoded_mem_write_enable $end
$var reg 1 . enable $end
$var reg 8 / mem_read_data [7:0] $end
$var reg 1 0 mem_read_ready $end
$var reg 1 1 mem_write_ready $end
$var reg 1 2 reset $end
$var reg 8 3 rs [7:0] $end
$var reg 8 4 rt [7:0] $end
$var integer 32 5 rd_cnt [31:0] $end
$var integer 32 6 rd_latency [31:0] $end
$var integer 32 7 tests_failed [31:0] $end
$var integer 32 8 tests_passed [31:0] $end
$var integer 32 9 wr_cnt [31:0] $end
$var integer 32 : wr_latency [31:0] $end
$scope module uut $end
$var wire 1 * clock $end
$var wire 3 ; core_state [2:0] $end
$var wire 1 , decoded_mem_read_enable $end
$var wire 1 - decoded_mem_write_enable $end
$var wire 1 . enable $end
$var wire 8 < mem_read_data [7:0] $end
$var wire 1 0 mem_read_ready $end
$var wire 1 1 mem_write_ready $end
$var wire 1 2 reset $end
$var wire 8 = rs [7:0] $end
$var wire 8 > rt [7:0] $end
$var parameter 2 ? LSU_DONE $end
$var parameter 2 @ LSU_IDLE $end
$var parameter 2 A LSU_REQUESTING $end
$var parameter 2 B LSU_WAITING $end
$var parameter 3 C REQUEST $end
$var parameter 3 D UPDATE $end
$var reg 8 E lsu_out [7:0] $end
$var reg 2 F lsu_state [1:0] $end
$var reg 8 G mem_read_address [7:0] $end
$var reg 1 $ mem_read_valid $end
$var reg 8 H mem_write_address [7:0] $end
$var reg 8 I mem_write_data [7:0] $end
$var reg 1 ! mem_write_valid $end
$upscope $end
$scope task check_signal $end
$var reg 256 J label [255:0] $end
$var integer 32 K actual [31:0] $end
$var integer 32 L expected [31:0] $end
$upscope $end
$scope task do_load $end
$var reg 8 M addr [7:0] $end
$var reg 1 N seen $end
$var integer 32 O guard [31:0] $end
$upscope $end
$scope task do_store $end
$var reg 8 P addr [7:0] $end
$var reg 1 Q seen $end
$var reg 8 R val [7:0] $end
$var integer 32 S guard [31:0] $end
$upscope $end
$upscope $end
$enddefinitions $end
$comment Show the parameter values. $end
$dumpall
b110 D
b11 C
b10 B
b1 A
b0 @
b11 ?
b110 )
b11 (
b10 '
$end
#0
$dumpvars
bx S
bx R
xQ
bx P
bx O
xN
bx M
bx L
bx K
bx J
bx I
bx H
bx G
bx F
bx E
b0 >
b0 =
b0 <
b10 ;
b1 :
b0 9
b0 8
b0 7
b1 6
b0 5
b0 4
b0 3
12
01
00
b0 /
0.
0-
0,
b10 +
0*
bx &
bx %
x$
bx #
bx "
x!
$end
#5
b0 &
b0 E
b0 "
b0 I
b0 #
b0 H
0!
b0 %
b0 G
0$
b0 F
1*
#10
0*
#15
1*
#20
0*
1.
02
b11 8
b101001001100101011100110110010101110100001110100010000001101101011001010110110101011111011101110111001001101001011101000110010101011111011101100110000101101100011010010110010000100000001111010010000000110000 J
b0 L
b0 K
#25
1*
#30
0*
b0 O
0N
b11 +
b11 ;
b10000 3
b10000 =
1,
b10000 M
#35
b1 F
1*
#40
0*
b1 O
#45
b10 F
b10000 %
b10000 G
1$
1*
#50
0*
1N
b10 O
#55
b1 5
1*
#60
0*
b11 O
#65
b0 5
b1000010 /
b1000010 <
10
1*
#70
0*
b100 O
#75
00
b11 F
b1000010 &
b1000010 E
0$
1*
#80
0*
b110 +
b110 ;
b101 O
#85
b0 F
1*
#90
0*
b10 +
b10 ;
0,
#95
1*
#100
0*
b0 O
0N
b11 +
b11 ;
b10001 3
b10001 =
1,
b10001 M
b101 8
b1001100010001000101001000111010001000000111001001100101011000010110010000100000011100100110010101110001011101010110010101110011011101000010000001100100011001010110000101110011011100110110010101110010011101000110010101100100 J
b0 L
b0 K
#105
b1 F
1*
#110
0*
b1 O
#115
b10 F
b10001 %
b10001 G
1$
1*
#120
0*
1N
b10 O
#125
b1 5
1*
#130
0*
b11 O
#135
b0 5
b111 /
b111 <
10
1*
#140
0*
b100 O
#145
b11 F
b111 &
b111 E
0$
00
1*
#150
0*
b110 +
b110 ;
b101 O
#155
b0 F
1*
#160
0*
b10 +
b10 ;
0,
#165
1*
#170
0*
b0 O
0N
b11 +
b11 ;
b10000000 3
b10000000 =
1,
b10000000 M
b110 8
b1001100010001000101001000100000010110110011000001111000001100010011000101011101001000000010110100111110001000000110110001110011011101010101111101101111011101010111010000100000001111010010000000110000011110000011000000110111 J
b111 L
b111 K
#175
b1 F
1*
#180
0*
b1 O
#185
b10 F
b10000000 %
b10000000 G
1$
1*
#190
0*
1N
b10 O
#195
b1 5
1*
#200
0*
b11 O
#205
b0 5
b11111110 /
b11111110 <
10
1*
#210
0*
b100 O
#215
00
b11 F
b11111110 &
b11111110 E
0$
1*
#220
0*
b110 +
b110 ;
b101 O
#225
b0 F
1*
#230
0*
b10 +
b10 ;
0,
#235
1*
#240
0*
b0 S
0Q
b11 +
b11 ;
b10011001 4
b10011001 >
b100000 3
b100000 =
1-
b10011001 R
b100000 P
b111 8
b1001100010001000101001000100000010110110011000001111000001110000011000001011101001000000010110100111110001000000110110001110011011101010101111101101111011101010111010000100000001111010010000000110000011110000100011001000101 J
b11111110 L
b11111110 K
#245
b1 F
1*
#250
0*
b1 S
#255
b10 F
b10011001 "
b10011001 I
b100000 #
b100000 H
1!
1*
#260
0*
1Q
b10 S
#265
b1 9
1*
#270
0*
b11 S
#275
b0 9
11
1*
#280
0*
b100 S
#285
b11 F
0!
01
1*
#290
0*
b110 +
b110 ;
b101 S
#295
b0 F
1*
#300
0*
b10 +
b10 ;
0-
#305
1*
#310
0*
b0 S
0Q
b11 +
b11 ;
b10101011 4
b10101011 >
b100001 3
b100001 =
1-
b10101011 R
b100001 P
b1001 8
b101001101010100010100100011101000100000011101110111001001101001011101000110010100100000011100100110010101110001011101010110010101110011011101000010000001100100011001010110000101110011011100110110010101110010011101000110010101100100 J
b0 L
b0 K
#315
b1 F
1*
#320
0*
b1 S
#325
b10 F
b10101011 "
b10101011 I
b100001 #
b100001 H
1!
1*
#330
0*
1Q
b10 S
#335
b1 9
1*
#340
0*
b11 S
#345
b0 9
11
1*
#350
0*
b100 S
#355
01
b11 F
0!
1*
#360
0*
b110 +
b110 ;
b101 S
#365
b0 F
1*
#370
0*
b10 +
b10 ;
0-
#375
1*
#380
0*
b0 O
0N
b11 +
b11 ;
b100000 3
b100000 =
1,
b100000 M
b1010 8
b10100110101010001010010001000000011000001111000010000010100001000100000001011010011111000100000010110110011000001111000001100100011000101011101 J
b10101011 L
b10101011 K
#385
b1 F
1*
#390
0*
b1 O
#395
b10 F
b100000 %
b100000 G
1$
1*
#400
0*
1N
b10 O
#405
b1 5
1*
#410
0*
b11 O
#415
b0 5
b10011001 /
b10011001 <
10
1*
#420
0*
b100 O
#425
b11 F
b10011001 &
b10011001 E
0$
00
1*
#430
0*
b110 +
b110 ;
b101 O
#435
b0 F
1*
#440
0*
b10 +
b10 ;
0,
#445
1*
#450
0*
b0 O
0N
b11 +
b11 ;
b10001 3
b10001 =
1,
b10001 M
b101 6
b1011 8
b110000101100011011010110010000000110000011110000011100100111001001000000010100001110011011101000110111101110010011001010010111101101100011011110110000101100100001000000111001001101111011101010110111001100100001011010111010001110010011010010111000000101001 J
b10011001 L
b10011001 K
#455
b1 F
1*
#460
0*
b1 O
#465
b10 F
b10001 %
b10001 G
1$
1*
#470
0*
1N
b10 O
#475
b1 5
1*
#480
0*
b11 O
#485
b10 5
1*
#490
0*
b100 O
#495
b11 5
1*
#500
0*
b101 O
#505
b100 5
1*
#510
0*
b110 O
#515
b101 5
1*
#520
0*
b111 O
#525
b0 5
b111 /
b111 <
10
1*
#530
0*
b1000 O
#535
00
b11 F
b111 &
b111 E
0$
1*
#540
0*
b110 +
b110 ;
b1001 O
#545
b0 F
1*
#550
0*
b10 +
b10 ;
0,
#555
1*
#560
0*
b11 +
b11 ;
b10000000 3
b10000000 =
1,
0.
b1 6
b1100 8
b110111101110111001000000100110001000100010100100010000001011011001100000111100000110001001100010101110100100000011100110111010001101001011011000110110000100000011100100110010101110100011101010111001001101110011100110010000000110000011110000011000000110111 J
b111 L
b111 K
#565
1*
#570
0*
#575
1*
#580
0*
#585
1*
#590
0*
#595
1*
#600
0*
#605
1*
#610
0*
1.
b10 +
b10 ;
0,
b1110 8
b11101000100000011011000111001101110101010111110110111101110101011101000010000001110101011011100110001101101000011000010110111001100111011001010110010000100000001010000111001101110100011010010110110001101100001000000011000001111000001100000011011100101001 J
b111 L
b111 K
#615
1*
#620
0*
b0 O
0N
b11 +
b11 ;
1,
b10000000 M
#625
b1 F
1*
#630
0*
b1 O
#635
b10 F
b10000000 %
b10000000 G
1$
1*
#640
0*
1N
b10 O
#645
b1 5
1*
#650
0*
b11 O
#655
b0 5
b11111110 /
b11111110 <
10
1*
#660
0*
b100 O
#665
b11 F
b11111110 &
b11111110 E
0$
00
1*
#670
0*
b110 +
b110 ;
b101 O
#675
b0 F
1*
#680
0*
b10 +
b10 ;
0,
#685
1*
#690
0*
12
b1111 8
b10100100110010100101101011001010110111001100001011000100110110001100101011001000011101000100000010011000100010001010010001000000101101100110000011110000011100000110000010111010010000000101101001111100010000000110000011110000100011001000101 J
b11111110 L
b11111110 K
#695
b0 /
b0 <
b0 &
b0 E
b0 "
b0 I
b0 #
b0 H
b0 %
b0 G
1*
#700
0*
02
b10010 8
b101001001100101011100110110010101110100001110100010000001101101011001010110110101011111011101110111001001101001011101000110010101011111011101100110000101101100011010010110010000100000001111010010000000110000 J
b0 L
b0 K
