src/pc.sv
`default_nettype none
`timescale 1ns/1ns

// PROGRAM COUNTER
// One PC per thread. Two responsibilities:
//   1. EXECUTE stage: compute next_pc (PC+1 by default, branch target on BRnzp)
//   2. UPDATE  stage: latch the NZP condition register from a CMP result
//
// NZP is set by CMP (decoded_nzp_write_enable=1, alu_out[2:0] = {N,Z,P}) and
// consumed by BRnzp (decoded_pc_mux=1, decoded_nzp = condition mask) to decide
// whether the branch is taken: taken iff (nzp & decoded_nzp) != 0.
//
// Threads can in principle diverge (each has its own PC), but we currently
// assume all threads in a block walk the same control flow.
module pc #(
    parameter DATA_BITS             = 8,
    parameter PROGRAM_MEM_ADDR_BITS = 8
) (
    input wire clock,                                      // Heartbeat - all updates on rising edge
    input wire reset,                                      // Force PC=0, NZP=0
    input wire enable,                                     // Is this thread active? (SIMT masking)

    // Pipeline state
    input wire [2:0] core_state,                           // Which stage is the core in?

    // Decoded control signals
    input wire [2:0] decoded_nzp,                          // BRnzp condition mask: which flags trigger branch
    input wire [DATA_BITS-1:0] decoded_immediate,          // Branch target address
    input wire decoded_nzp_write_enable,                   // CMP wants to write NZP this UPDATE
    input wire decoded_pc_mux,                             // 0 = PC+1, 1 = branch target

    // ALU output - bottom 3 bits are the fresh NZP result from a CMP that just executed
    input wire [DATA_BITS-1:0] alu_out,

    // PC interface
    input  wire [PROGRAM_MEM_ADDR_BITS-1:0] current_pc,
    output reg  [PROGRAM_MEM_ADDR_BITS-1:0] next_pc
);

    // Pipeline stages we care about
    localparam EXECUTE = 3'b101;
    localparam UPDATE  = 3'b110;

    // Condition register: {N, Z, P} - latched from the most recent CMP
    reg [2:0] nzp;

    always @(posedge clock) begin
        if (reset) begin
            nzp     <= 3'b000;
            next_pc <= {PROGRAM_MEM_ADDR_BITS{1'b0}};
        end else if (enable) begin
            // EXECUTE stage: choose next PC
            if (core_state == EXECUTE) begin
                if (decoded_pc_mux) begin
                    // BRnzp: branch only if any latched flag matches the requested mask
                    if ((nzp & decoded_nzp) != 3'b000)
                        next_pc <= decoded_immediate;
                    else
                        next_pc <= current_pc + 1;
                end else begin
                    // Default: sequential execution
                    next_pc <= current_pc + 1;
                end
            end

            // UPDATE stage: latch new NZP flags from a CMP result
            if (core_state == UPDATE) begin
                if (decoded_nzp_write_enable) begin
                    nzp <= alu_out[2:0];
                end
            end
        end
    end

endmodule

test/pc_tb.sv
`default_nettype none
`timescale 1ns/1ns

module pc_tb;
    reg        clock;
    reg        reset;
    reg        enable;
    reg  [2:0] core_state;
    reg  [2:0] decoded_nzp;
    reg  [7:0] decoded_immediate;
    reg        decoded_nzp_write_enable;
    reg        decoded_pc_mux;
    reg  [7:0] alu_out;
    reg  [7:0] current_pc;

    wire [7:0] next_pc;

    pc #(
        .DATA_BITS             (8),
        .PROGRAM_MEM_ADDR_BITS (8)
    ) uut (
        .clock                    (clock),
        .reset                    (reset),
        .enable                   (enable),
        .core_state               (core_state),
        .decoded_nzp              (decoded_nzp),
        .decoded_immediate        (decoded_immediate),
        .decoded_nzp_write_enable (decoded_nzp_write_enable),
        .decoded_pc_mux           (decoded_pc_mux),
        .alu_out                  (alu_out),
        .current_pc               (current_pc),
        .next_pc                  (next_pc)
    );

    // Clock generation: 10ns period (100MHz)
    always #5 clock = ~clock;

    // Pipeline stages
    localparam FETCH   = 3'b000;
    localparam EXECUTE = 3'b101;
    localparam UPDATE  = 3'b110;

    // ALU comparison output encoding: {5'b0, N, Z, P}
    localparam [7:0] ALU_NEG  = 8'b00000_100;
    localparam [7:0] ALU_ZERO = 8'b00000_010;
    localparam [7:0] ALU_POS  = 8'b00000_001;

    integer tests_passed = 0;
    integer tests_failed = 0;

    task check_signal;
        input integer actual;
        input integer expected;
        input [255:0] label;
        begin
            if (actual === expected) begin
                $display("[PASS] %s", label);
                tests_passed = tests_passed + 1;
            end else begin
                $display("[FAIL] %s: expected %0d, got %0d", label, expected, actual);
                tests_failed = tests_failed + 1;
            end
        end
    endtask

    // Drive a CMP-style UPDATE: latch nzp from alu_out[2:0]
    task latch_nzp;
        input [7:0] alu_value;
        begin
            decoded_nzp_write_enable = 1;
            alu_out                  = alu_value;
            core_state               = UPDATE;
            #10;
            decoded_nzp_write_enable = 0;
            core_state               = FETCH;
        end
    endtask

    // Drive an EXECUTE for a sequential (non-branch) instruction
    task step_sequential;
        input [7:0] pc_in;
        begin
            decoded_pc_mux    = 0;
            decoded_nzp       = 3'b000;
            decoded_immediate = 8'd0;
            current_pc        = pc_in;
            core_state        = EXECUTE;
            #10;
            core_state        = FETCH;
        end
    endtask

    // Drive an EXECUTE for a BRnzp instruction
    task step_branch;
        input [7:0] pc_in;
        input [2:0] nzp_mask;
        input [7:0] target;
        begin
            decoded_pc_mux    = 1;
            decoded_nzp       = nzp_mask;
            decoded_immediate = target;
            current_pc        = pc_in;
            core_state        = EXECUTE;
            #10;
            core_state        = FETCH;
        end
    endtask

    initial begin
        $dumpfile("pc_tb.vcd");
        $dumpvars(0, pc_tb);

        clock                    = 0;
        reset                    = 1;
        enable                   = 0;
        core_state               = FETCH;
        decoded_nzp              = 3'b000;
        decoded_immediate        = 8'd0;
        decoded_nzp_write_enable = 0;
        decoded_pc_mux           = 0;
        alu_out                  = 8'd0;
        current_pc               = 8'd0;

        $display("\n========================================");
        $display("Program Counter Testbench Starting");
        $display("========================================\n");

        // Reset sequence
        #20;
        reset  = 0;
        enable = 1;
        #10;

        check_signal(next_pc, 0, "Reset: next_pc = 0");

        // ==========================================
        // Sequential PC Increment
        // ==========================================
        $display("\n--- Sequential PC Increment ---\n");

        step_sequential(8'd0);
        check_signal(next_pc, 1, "Seq: PC=0 -> next_pc=1");

        step_sequential(8'd1);
        check_signal(next_pc, 2, "Seq: PC=1 -> next_pc=2");

        step_sequential(8'd42);
        check_signal(next_pc, 43, "Seq: PC=42 -> next_pc=43");

        step_sequential(8'd255);
        check_signal(next_pc, 0, "Seq: PC=255 -> wraps to 0 (8-bit)");

        // ==========================================
        // BRnzp with empty NZP - never taken
        // ==========================================
        $display("\n--- BRnzp with empty NZP ---\n");

        // After reset NZP=0; (0 & anything) == 0, so branch never taken
        step_branch(8'd10, 3'b111, 8'd99);
        check_signal(next_pc, 11, "BR: NZP=000, mask=111 -> not taken (PC+1)");

        // ==========================================
        // CMP -> NEGATIVE, branch on n
        // ==========================================
        $display("\n--- NZP=N ---\n");

        latch_nzp(ALU_NEG);

        step_branch(8'd20, 3'b100, 8'd80);
        check_signal(next_pc, 80, "BR: NZP=N, mask=n   -> taken to 80");

        step_branch(8'd20, 3'b010, 8'd80);
        check_signal(next_pc, 21, "BR: NZP=N, mask=z   -> not taken");

        step_branch(8'd20, 3'b001, 8'd80);
        check_signal(next_pc, 21, "BR: NZP=N, mask=p   -> not taken");

        step_branch(8'd20, 3'b111, 8'd123);
        check_signal(next_pc, 123, "BR: NZP=N, mask=nzp -> taken to 123");

        // ==========================================
        // CMP -> ZERO, branch on z
        // ==========================================
        $display("\n--- NZP=Z ---\n");

        latch_nzp(ALU_ZERO);

        step_branch(8'd30, 3'b010, 8'd200);
        check_signal(next_pc, 200, "BR: NZP=Z, mask=z   -> taken to 200");

        step_branch(8'd30, 3'b101, 8'd200);
        check_signal(next_pc, 31, "BR: NZP=Z, mask=np  -> not taken");

        // ==========================================
        // CMP -> POSITIVE, branch on p
        // ==========================================
        $display("\n--- NZP=P ---\n");

        latch_nzp(ALU_POS);

        step_branch(8'd40, 3'b001, 8'd150);
        check_signal(next_pc, 150, "BR: NZP=P, mask=p   -> taken to 150");

        step_branch(8'd40, 3'b110, 8'd150);
        check_signal(next_pc, 41, "BR: NZP=P, mask=nz  -> not taken");

        // ==========================================
        // NZP persists until next CMP
        // ==========================================
        $display("\n--- NZP persistence ---\n");

        // NZP is currently P; a sequential step shouldn't clobber it
        step_sequential(8'd50);
        check_signal(next_pc, 51, "Seq doesn't disturb NZP");

        step_branch(8'd50, 3'b001, 8'd77);
        check_signal(next_pc, 77, "BR: P still latched -> taken to 77");

        // ==========================================
        // nzp_write_enable=0 doesn't change NZP
        // ==========================================
        $display("\n--- NZP write-protect ---\n");

        // Try to "fake" updating NZP without the enable bit
        decoded_nzp_write_enable = 0;
        alu_out                  = ALU_NEG;
        core_state               = UPDATE;
        #10;
        core_state               = FETCH;

        // Should still be POSITIVE - branch on p must succeed
        step_branch(8'd60, 3'b001, 8'd88);
        check_signal(next_pc, 88, "BR: NZP unchanged (still P) -> taken to 88");

        // ==========================================
        // Enable masking: PC frozen when disabled
        // ==========================================
        $display("\n--- Enable Masking ---\n");

        enable = 0;
        step_sequential(8'd100);
        check_signal(next_pc, 88, "Enable=0: next_pc holds previous value");

        enable = 1;
        step_sequential(8'd100);
        check_signal(next_pc, 101, "Enable=1: next_pc updates again");

        // ==========================================
        // Reset clears NZP and next_pc
        // ==========================================
        $display("\n--- Reset Clears State ---\n");

        latch_nzp(ALU_POS);   // make NZP non-zero before reset
        reset = 1;
        #10;
        check_signal(next_pc, 0, "Reset: next_pc = 0");

        reset  = 0;
        enable = 1;
        // After reset NZP=0 - any BRnzp must NOT take
        step_branch(8'd10, 3'b111, 8'd200);
        check_signal(next_pc, 11, "Reset cleared NZP - BR not taken");

        // ==========================================
        // Summary
        // ==========================================
        #20;
        $display("\n========================================");
        $display("Test Summary");
        $display("========================================");
        $display("Passed: %d", tests_passed);
        $display("Failed: %d", tests_failed);
        $display("========================================\n");

        if (tests_failed == 0)
            $display("ALL TESTS PASSED!\n");
        else
            $display("SOME TESTS FAILED!\n");

        $finish;
    end

endmodule

test/pc_tb.vcd
$date
	Sun Apr 19 08:50:20 2026
$end
$version
	Icarus Verilog
$end
$timescale
	1ns
$end
$scope module pc_tb $end
$var wire 8 ! next_pc [7:0] $end
$var parameter 8 " ALU_NEG $end
$var parameter 8 # ALU_POS $end
$var parameter 8 $ ALU_ZERO $end
$var parameter 3 % EXECUTE $end
$var parameter 3 & FETCH $end
$var parameter 3 ' UPDATE $end
$var reg 8 ( alu_out [7:0] $end
$var reg 1 ) clock $end
$var reg 3 * core_state [2:0] $end
$var reg 8 + current_pc [7:0] $end
$var reg 8 , decoded_immediate [7:0] $end
$var reg 3 - decoded_nzp [2:0] $end
$var reg 1 . decoded_nzp_write_enable $end
$var reg 1 / decoded_pc_mux $end
$var reg 1 0 enable $end
$var reg 1 1 reset $end
$var integer 32 2 tests_failed [31:0] $end
$var integer 32 3 tests_passed [31:0] $end
$scope module uut $end
$var wire 8 4 alu_out [7:0] $end
$var wire 1 ) clock $end
$var wire 3 5 core_state [2:0] $end
$var wire 8 6 current_pc [7:0] $end
$var wire 8 7 decoded_immediate [7:0] $end
$var wire 3 8 decoded_nzp [2:0] $end
$var wire 1 . decoded_nzp_write_enable $end
$var wire 1 / decoded_pc_mux $end
$var wire 1 0 enable $end
$var wire 1 1 reset $end
$var parameter 32 9 DATA_BITS $end
$var parameter 3 : EXECUTE $end
$var parameter 32 ; PROGRAM_MEM_ADDR_BITS $end
$var parameter 3 < UPDATE $end
$var reg 8 = next_pc [7:0] $end
$var reg 3 > nzp [2:0] $end
$upscope $end
$scope task check_signal $end
$var reg 256 ? label [255:0] $end
$var integer 32 @ actual [31:0] $end
$var integer 32 A expected [31:0] $end
$upscope $end
$scope task latch_nzp $end
$var reg 8 B alu_value [7:0] $end
$upscope $end
$scope task step_branch $end
$var reg 3 C nzp_mask [2:0] $end
$var reg 8 D pc_in [7:0] $end
$var reg 8 E target [7:0] $end
$upscope $end
$scope task step_sequential $end
$var reg 8 F pc_in [7:0] $end
$upscope $end
$upscope $end
$enddefinitions $end
$comment Show the parameter values. $end
$dumpall
b110 <
b1000 ;
b101 :
b1000 9
b110 '
b0 &
b101 %
b10 $
b1 #
b100 "
$end
#0
$dumpvars
bx F
bx E
bx D
bx C
bx B
bx A
bx @
bx ?
bx >
bx =
b0 8
b0 7
b0 6
b0 5
b0 4
b0 3
b0 2
11
00
0/
0.
b0 -
b0 ,
b0 +
b0 *
0)
b0 (
bx !
$end
#5
b0 !
b0 =
b0 >
1)
#10
0)
#15
1)
#20
0)
10
01
#25
1)
#30
0)
b101 *
b101 5
b0 F
b1 3
b10100100110010101110011011001010111010000111010001000000110111001100101011110000111010001011111011100000110001100100000001111010010000000110000 ?
b0 A
b0 @
#35
b1 !
b1 =
1)
#40
0)
b1 +
b1 6
b1 F
b10 3
b1010011011001010111000100111010001000000101000001000011001111010011000000100000001011010011111000100000011011100110010101111000011101000101111101110000011000110011110100110001 ?
b1 A
b1 @
b101 *
b101 5
#45
b10 !
b10 =
1)
#50
0)
b101010 +
b101010 6
b101010 F
b11 3
b1010011011001010111000100111010001000000101000001000011001111010011000100100000001011010011111000100000011011100110010101111000011101000101111101110000011000110011110100110010 ?
b10 A
b10 @
b101 *
b101 5
#55
b101011 !
b101011 =
1)
#60
0)
b11111111 +
b11111111 6
b11111111 F
b100 3
b10100110110010101110001001110100010000001010000010000110011110100110100001100100010000000101101001111100010000001101110011001010111100001110100010111110111000001100011001111010011010000110011 ?
b101011 A
b101011 @
b101 *
b101 5
#65
b0 !
b0 =
1)
#70
0)
b1010 +
b1010 6
b1100011 ,
b1100011 7
b111 -
b111 8
1/
b1100011 E
b111 C
b1010 D
b101 3
b110010101110001001110100010000001010000010000110011110100110010001101010011010100100000001011010011111000100000011101110111001001100001011100000111001100100000011101000110111100100000001100000010000000101000001110000010110101100010011010010111010000101001 ?
b0 A
b0 @
b101 *
b101 5
#75
b1011 !
b1011 =
1)
#80
0)
b100 (
b100 4
1.
b100 B
b110 3
b11000000110000001011000010000001101101011000010111001101101011001111010011000100110001001100010010000000101101001111100010000001101110011011110111010000100000011101000110000101101011011001010110111000100000001010000101000001000011001010110011000100101001 ?
b1011 A
b1011 @
b110 *
b110 5
#85
b100 >
1)
#90
0)
b10100 +
b10100 6
b1010000 ,
b1010000 7
b100 -
b100 8
b1010000 E
b100 C
b10100 D
b101 *
b101 5
0.
#95
b1010000 !
b1010000 =
1)
#100
0)
b10 -
b10 8
b10 C
b111 3
b11101000100000010011100101101001010000001111010100111000101100001000000110110101100001011100110110101100111101011011100010000000100000001000000010110100111110001000000111010001100001011010110110010101101110001000000111010001101111001000000011100000110000 ?
b1010000 A
b1010000 @
b101 *
b101 5
#105
b10101 !
b10101 =
1)
#110
0)
b1 -
b1 8
b1 C
b1000 3
b100001001010010001110100010000001001110010110100101000000111101010011100010110000100000011011010110000101110011011010110011110101111010001000000010000000100000001011010011111000100000011011100110111101110100001000000111010001100001011010110110010101101110 ?
b10101 A
b10101 @
b101 *
b101 5
#115
1)
#120
0)
b1111011 ,
b1111011 7
b111 -
b111 8
b1111011 E
b111 C
b1001 3
b100001001010010001110100010000001001110010110100101000000111101010011100010110000100000011011010110000101110011011010110011110101110000001000000010000000100000001011010011111000100000011011100110111101110100001000000111010001100001011010110110010101101110 ?
b101 *
b101 5
#125
b1111011 !
b1111011 =
1)
#130
0)
b10 (
b10 4
1.
b10 B
b1010 3
b10000001001110010110100101000000111101010011100010110000100000011011010110000101110011011010110011110101101110011110100111000000100000001011010011111000100000011101000110000101101011011001010110111000100000011101000110111100100000001100010011001000110011 ?
b1111011 A
b1111011 @
b110 *
b110 5
#135
b10 >
1)
#140
0)
b11110 +
b11110 6
b11001000 ,
b11001000 7
b10 -
b10 8
b11001000 E
b10 C
b11110 D
b101 *
b101 5
0.
#145
b11001000 !
b11001000 =
1)
#150
0)
b101 -
b101 8
b101 C
b1011 3
b10000001001110010110100101000000111101010110100010110000100000011011010110000101110011011010110011110101111010001000000010000000100000001011010011111000100000011101000110000101101011011001010110111000100000011101000110111100100000001100100011000000110000 ?
b11001000 A
b11001000 @
b101 *
b101 5
#155
b11111 !
b11111 =
1)
#160
0)
b1 (
b1 4
1.
b1 B
b1100 3
b100001001010010001110100010000001001110010110100101000000111101010110100010110000100000011011010110000101110011011010110011110101101110011100000010000000100000001011010011111000100000011011100110111101110100001000000111010001100001011010110110010101101110 ?
b11111 A
b11111 @
b110 *
b110 5
#165
b1 >
1)
#170
0)
b101000 +
b101000 6
b10010110 ,
b10010110 7
b1 -
b1 8
b10010110 E
b1 C
b101000 D
b101 *
b101 5
0.
#175
b10010110 !
b10010110 =
1)
#180
0)
b110 -
b110 8
b110 C
b1101 3
b10000001001110010110100101000000111101010100000010110000100000011011010110000101110011011010110011110101110000001000000010000000100000001011010011111000100000011101000110000101101011011001010110111000100000011101000110111100100000001100010011010100110000 ?
b10010110 A
b10010110 @
b101 *
b101 5
#185
b101001 !
b101001 =
1)
#190
0)
b110010 +
b110010 6
b0 ,
b0 7
b0 -
b0 8
0/
b110010 F
b1110 3
b100001001010010001110100010000001001110010110100101000000111101010100000010110000100000011011010110000101110011011010110011110101101110011110100010000000100000001011010011111000100000011011100110111101110100001000000111010001100001011010110110010101101110 ?
b101001 A
b101001 @
b101 *
b101 5
#195
b110011 !
b110011 =
1)
#200
0)
b1001101 ,
b1001101 7
b1 -
b1 8
1/
b1001101 E
b1 C
b110010 D
b1111 3
b101001101100101011100010010000001100100011011110110010101110011011011100010011101110100001000000110010001101001011100110111010001110101011100100110001000100000010011100101101001010000 ?
b110011 A
b110011 @
b101 *
b101 5
#205
b1001101 !
b1001101 =
1)
#210
0)
b100 (
b100 4
b10000 3
b11101000100000010100000010000001110011011101000110100101101100011011000010000001101100011000010111010001100011011010000110010101100100001000000010110100111110001000000111010001100001011010110110010101101110001000000111010001101111001000000011011100110111 ?
b1001101 A
b1001101 @
b110 *
b110 5
#215
1)
#220
0)
b111100 +
b111100 6
b1011000 ,
b1011000 7
b1011000 E
b111100 D
b101 *
b101 5
#225
b1011000 !
b1011000 =
1)
#230
0)
b1100100 +
b1100100 6
b0 ,
b0 7
b0 -
b0 8
0/
b1100100 F
00
b10001 3
b110001101101000011000010110111001100111011001010110010000100000001010000111001101110100011010010110110001101100001000000101000000101001001000000010110100111110001000000111010001100001011010110110010101101110001000000111010001101111001000000011100000111000 ?
b1011000 A
b1011000 @
b101 *
b101 5
#235
1)
#240
0)
10
b10010 3
b11110100110000001110100010000001101110011001010111100001110100010111110111000001100011001000000110100001101111011011000110010001110011001000000111000001110010011001010111011001101001011011110111010101110011001000000111011001100001011011000111010101100101 ?
b101 *
b101 5
#245
b1100101 !
b1100101 =
1)
#250
0)
b1 (
b1 4
1.
b10011 3
b1000101011011100110000101100010011011000110010100111101001100010011101000100000011011100110010101111000011101000101111101110000011000110010000001110101011100000110010001100001011101000110010101110011001000000110000101100111011000010110100101101110 ?
b1100101 A
b1100101 @
b110 *
b110 5
#255
1)
#260
0)
11
b0 *
b0 5
0.
#265
b0 !
b0 =
b0 >
1)
#270
0)
b101 *
b101 5
b1010 +
b1010 6
b11001000 ,
b11001000 7
b111 -
b111 8
1/
b11001000 E
b111 C
b1010 D
01
b10100 3
b10100100110010101110011011001010111010000111010001000000110111001100101011110000111010001011111011100000110001100100000001111010010000000110000 ?
b0 A
b0 @
#275
b1011 !
b1011 =
1)
#280
0)
b10101 3
b101001001100101011100110110010101110100001000000110001101101100011001010110000101110010011001010110010000100000010011100101101001010000001000000010110100100000010000100101001000100000011011100110111101110100001000000111010001100001011010110110010101101110 ?
b1011 A
b1011 @
b0 *
b0 5
