src/registers.sv
`default_nettype none
`timescale 1ns/1ns

// REGISTER FILE
// Each thread has its own register file: 13 general-purpose + 3 read-only registers
// Read-only registers: R13 = %blockIdx, R14 = %blockDim, R15 = %threadIdx
module registers #(
    parameter THREADS_PER_BLOCK = 4,
    parameter THREAD_ID = 0,
    parameter DATA_BITS = 8
) (
    input wire clock,                                // Clock signal
    input wire reset,                                // Reset all registers to 0
    input wire enable,                               // Is this thread active? (inactive if block has fewer threads)

    // Kernel execution context
    input wire [7:0] block_id,                        // Current block being executed

    // Core pipeline state
    input wire [2:0] core_state,                      // 3-bit state: which stage is the core in?

    // Decoded instruction signals
    input wire [3:0] decoded_rd_address,              // 4-bit: destination register address (R0-R15)
    input wire [3:0] decoded_rs_address,              // 4-bit: source register 1 address
    input wire [3:0] decoded_rt_address,              // 4-bit: source register 2 address

    // Control signals from decoder
    input wire decoded_reg_write_enable,              // 1-bit: should we write to rd?
    input wire [1:0] decoded_reg_input_selector,      // 2-bit: where does the write data come from?
    input wire [DATA_BITS-1:0] decoded_immediate,     // 8-bit: immediate/constant value from instruction

    // Data inputs from other units
    input wire [DATA_BITS-1:0] alu_out,               // 8-bit: result from ALU (arithmetic/comparison)
    input wire [DATA_BITS-1:0] lsu_out,               // 8-bit: result from LSU (memory load)

    // Register outputs for operands
    output reg [7:0] rs,                             // 8-bit: value of source register 1
    output reg [7:0] rt                              // 8-bit: value of source register 2
);

    // Write data source selection
    localparam ARITHMETIC = 2'b00,   // ALU result (ADD, SUB, MUL, DIV)
               MEMORY     = 2'b01,   // LSU result (LDR)
               CONSTANT   = 2'b10;   // Immediate value (CONST)

    // Core pipeline stages we care about
    localparam REQUEST = 3'b011;     // Read rs/rt from register file
    localparam UPDATE  = 3'b110;     // Write result back to rd

    // 16 registers per thread (R0-R12 writable, R13-R15 read-only)
    reg [7:0] registers [15:0];

    integer i;

    always @(posedge clock) begin
        if (reset) begin
            rs <= 8'b0;
            rt <= 8'b0;

            // Clear all general-purpose registers
            for (i = 0; i < 13; i = i + 1) begin
                registers[i] <= 8'b0;
            end

            // Initialize read-only registers
            registers[13] <= 8'b0;              // %blockIdx (set per block dispatch)
            registers[14] <= THREADS_PER_BLOCK;  // %blockDim (fixed at synthesis)
            registers[15] <= THREAD_ID;          // %threadIdx (fixed at synthesis)
        end else if (enable) begin
            // Keep block_id in sync (updated each dispatch)
            registers[13] <= block_id;

            // REQUEST stage: read source registers into rs/rt
            if (core_state == REQUEST) begin
                rs <= registers[decoded_rs_address];
                rt <= registers[decoded_rt_address];
            end

            // UPDATE stage: write result back to destination register
            if (core_state == UPDATE) begin
                // Only general-purpose registers (R0-R12) are writable
                if (decoded_reg_write_enable && decoded_rd_address < 13) begin
                    case (decoded_reg_input_selector)
                        ARITHMETIC: registers[decoded_rd_address] <= alu_out;
                        MEMORY:     registers[decoded_rd_address] <= lsu_out;
                        CONSTANT:   registers[decoded_rd_address] <= decoded_immediate;
                    endcase
                end
            end
        end
    end

endmodule

test/registers_tb.sv
`default_nettype none
`timescale 1ns/1ns

module registers_tb;
    reg        clock;
    reg        reset;
    reg        enable;
    reg  [7:0] block_id;
    reg  [2:0] core_state;
    reg  [3:0] decoded_rd_address;
    reg  [3:0] decoded_rs_address;
    reg  [3:0] decoded_rt_address;
    reg        decoded_reg_write_enable;
    reg  [1:0] decoded_reg_input_selector;
    reg  [7:0] decoded_immediate;
    reg  [7:0] alu_out;
    reg  [7:0] lsu_out;

    wire [7:0] rs;
    wire [7:0] rt;

    // Use non-zero THREAD_ID so we can distinguish it from a zero default
    localparam THREADS_PER_BLOCK = 4;
    localparam THREAD_ID         = 2;

    registers #(
        .THREADS_PER_BLOCK (THREADS_PER_BLOCK),
        .THREAD_ID         (THREAD_ID),
        .DATA_BITS         (8)
    ) uut (
        .clock                      (clock),
        .reset                      (reset),
        .enable                     (enable),
        .block_id                   (block_id),
        .core_state                 (core_state),
        .decoded_rd_address         (decoded_rd_address),
        .decoded_rs_address         (decoded_rs_address),
        .decoded_rt_address         (decoded_rt_address),
        .decoded_reg_write_enable   (decoded_reg_write_enable),
        .decoded_reg_input_selector (decoded_reg_input_selector),
        .decoded_immediate          (decoded_immediate),
        .alu_out                    (alu_out),
        .lsu_out                    (lsu_out),
        .rs                         (rs),
        .rt                         (rt)
    );

    // Clock generation: 10ns period (100MHz)
    always #5 clock = ~clock;

    // Pipeline stages
    localparam REQUEST = 3'b011;
    localparam UPDATE  = 3'b110;

    // Write source selection
    localparam ARITHMETIC = 2'b00;
    localparam MEMORY     = 2'b01;
    localparam CONSTANT   = 2'b10;

    integer tests_passed = 0;
    integer tests_failed = 0;

    task check_signal;
        input integer actual;
        input integer expected;
        input [255:0] label;
        begin
            if (actual === expected) begin
                $display("[PASS] %s", label);
                tests_passed = tests_passed + 1;
            end else begin
                $display("[FAIL] %s: expected %0d, got %0d", label, expected, actual);
                tests_failed = tests_failed + 1;
            end
        end
    endtask

    // Write a value into a register via the UPDATE stage
    task write_reg;
        input [3:0] rd;
        input [1:0] src;
        input [7:0] val_alu;
        input [7:0] val_lsu;
        input [7:0] val_imm;
        begin
            decoded_reg_write_enable   = 1;
            decoded_rd_address         = rd;
            decoded_reg_input_selector = src;
            alu_out                    = val_alu;
            lsu_out                    = val_lsu;
            decoded_immediate          = val_imm;
            core_state                 = UPDATE;
            #10;
            decoded_reg_write_enable   = 0;
        end
    endtask

    // Latch rs from a register address via the REQUEST stage
    task read_rs;
        input [3:0] addr;
        begin
            decoded_rs_address = addr;
            core_state         = REQUEST;
            #10;
        end
    endtask

    // Latch rt from a register address via the REQUEST stage
    task read_rt;
        input [3:0] addr;
        begin
            decoded_rt_address = addr;
            core_state         = REQUEST;
            #10;
        end
    endtask

    initial begin
        $dumpfile("registers_tb.vcd");
        $dumpvars(0, registers_tb);

        clock                      = 0;
        reset                      = 1;
        enable                     = 0;
        block_id                   = 8'd0;
        core_state                 = 3'b000;
        decoded_rd_address         = 4'd0;
        decoded_rs_address         = 4'd0;
        decoded_rt_address         = 4'd0;
        decoded_reg_write_enable   = 0;
        decoded_reg_input_selector = 2'b00;
        decoded_immediate          = 8'd0;
        alu_out                    = 8'd0;
        lsu_out                    = 8'd0;

        $display("\n========================================");
        $display("Register File Testbench Starting");
        $display("(THREAD_ID=%0d, THREADS_PER_BLOCK=%0d)", THREAD_ID, THREADS_PER_BLOCK);
        $display("========================================\n");

        // Reset sequence
        #20;
        reset  = 0;
        enable = 1;
        #10;

        // ==========================================
        // Test Reset Values (read-only registers)
        // ==========================================
        $display("--- Reset Values ---\n");

        read_rs(14);
        check_signal(rs, THREADS_PER_BLOCK, "Reset: R14 (%blockDim) = THREADS_PER_BLOCK");

        read_rs(15);
        check_signal(rs, THREAD_ID, "Reset: R15 (%threadIdx) = THREAD_ID");

        read_rs(13);
        check_signal(rs, 0, "Reset: R13 (%blockIdx) = 0");

        // ==========================================
        // Test Write via CONSTANT, Read Back
        // ==========================================
        $display("\n--- Write via CONSTANT ---\n");

        write_reg(4'd0, CONSTANT, 8'd0, 8'd0, 8'd42);
        read_rs(4'd0);
        check_signal(rs, 42, "CONST: R0 = 42");

        write_reg(4'd7, CONSTANT, 8'd0, 8'd0, 8'd200);
        read_rs(4'd7);
        check_signal(rs, 200, "CONST: R7 = 200");

        // ==========================================
        // Test Write via ALU (ARITHMETIC), Read Back
        // ==========================================
        $display("\n--- Write via ALU (ARITHMETIC) ---\n");

        write_reg(4'd1, ARITHMETIC, 8'd99, 8'd0, 8'd0);
        read_rs(4'd1);
        check_signal(rs, 99, "ALU: R1 = 99");

        write_reg(4'd5, ARITHMETIC, 8'd255, 8'd0, 8'd0);
        read_rs(4'd5);
        check_signal(rs, 255, "ALU: R5 = 255");

        // ==========================================
        // Test Write via Memory (LSU), Read Back
        // ==========================================
        $display("\n--- Write via Memory (MEMORY) ---\n");

        write_reg(4'd2, MEMORY, 8'd0, 8'd173, 8'd0);
        read_rs(4'd2);
        check_signal(rs, 173, "MEM: R2 = 173");

        // ==========================================
        // Test Two-Operand Read (rs and rt simultaneously)
        // ==========================================
        $display("\n--- Two-Operand Read ---\n");

        write_reg(4'd3, CONSTANT, 8'd0, 8'd0, 8'd77);
        write_reg(4'd4, CONSTANT, 8'd0, 8'd0, 8'd88);

        decoded_rs_address = 4'd3;
        decoded_rt_address = 4'd4;
        core_state         = REQUEST;
        #10;
        check_signal(rs, 77, "Two-op: rs = R3 = 77");
        check_signal(rt, 88, "Two-op: rt = R4 = 88");

        // ==========================================
        // Test Read-Only Protection (R13, R14, R15)
        // ==========================================
        $display("\n--- Read-Only Protection ---\n");

        // Attempt to overwrite R14 (%blockDim)
        write_reg(4'd14, CONSTANT, 8'd0, 8'd0, 8'd99);
        read_rs(4'd14);
        check_signal(rs, THREADS_PER_BLOCK, "Read-only: R14 unchanged after write attempt");

        // Attempt to overwrite R15 (%threadIdx)
        write_reg(4'd15, CONSTANT, 8'd0, 8'd0, 8'd99);
        read_rs(4'd15);
        check_signal(rs, THREAD_ID, "Read-only: R15 unchanged after write attempt");

        // ==========================================
        // Test Block ID Update (R13 = %blockIdx)
        // ==========================================
        $display("\n--- Block ID Update ---\n");

        block_id   = 8'd7;
        core_state = 3'b000;   // Any non-REQUEST/UPDATE state - R13 still updates
        #10;
        read_rs(4'd13);
        check_signal(rs, 7, "BlockID: R13 = block_id = 7");

        block_id = 8'd15;
        #10;
        read_rs(4'd13);
        check_signal(rs, 15, "BlockID: R13 updates to 15");

        // ==========================================
        // Test Enable Masking
        // ==========================================
        $display("\n--- Enable Masking ---\n");

        // Establish a known value in rs (R0 = 42)
        read_rs(4'd0);
        check_signal(rs, 42, "Enable setup: rs = R0 = 42");

        // Disable thread - REQUEST should not update rs even if address changes
        enable             = 0;
        decoded_rs_address = 4'd7;   // R7 = 200 (written earlier)
        core_state         = REQUEST;
        #10;
        check_signal(rs, 42, "Enable=0: rs holds previous value (not updated to R7=200)");

        // Re-enable - now the read should go through
        enable = 1;
        #10;
        check_signal(rs, 200, "Enable=1: rs updates to R7 = 200");

        // ==========================================
        // Test Reset Clears General-Purpose Registers
        // ==========================================
        $display("\n--- Reset Clears Registers ---\n");

        reset = 1;
        #10;
        check_signal(rs, 0, "Reset: rs output = 0");
        reset  = 0;
        enable = 1;

        // R0 was 42 before reset - should now be 0
        read_rs(4'd0);
        check_signal(rs, 0, "Reset: R0 = 0 after reset");

        // Read-only registers restore to their parameter values
        read_rs(4'd14);
        check_signal(rs, THREADS_PER_BLOCK, "Reset: R14 restored to THREADS_PER_BLOCK");

        read_rs(4'd15);
        check_signal(rs, THREAD_ID, "Reset: R15 restored to THREAD_ID");

        // ==========================================
        // Summary
        // ==========================================
        #20;
        $display("\n========================================");
        $display("Test Summary");
        $display("========================================");
        $display("Passed: %d", tests_passed);
        $display("Failed: %d", tests_failed);
        $display("========================================\n");

        if (tests_failed == 0)
            $display("ALL TESTS PASSED!\n");
        else
            $display("SOME TESTS FAILED!\n");

        $finish;
    end

endmodule

test/registers_tb.vcd
$date
	Sat Mar  7 20:28:13 2026
$end
$version
	Icarus Verilog
$end
$timescale
	1ns
$end
$scope module registers_tb $end
$var wire 8 ! rt [7:0] $end
$var wire 8 " rs [7:0] $end
$var parameter 2 # ARITHMETIC $end
$var parameter 2 $ CONSTANT $end
$var parameter 2 % MEMORY $end
$var parameter 3 & REQUEST $end
$var parameter 32 ' THREADS_PER_BLOCK $end
$var parameter 32 ( THREAD_ID $end
$var parameter 3 ) UPDATE $end
$var reg 8 * alu_out [7:0] $end
$var reg 8 + block_id [7:0] $end
$var reg 1 , clock $end
$var reg 3 - core_state [2:0] $end
$var reg 8 . decoded_immediate [7:0] $end
$var reg 4 / decoded_rd_address [3:0] $end
$var reg 2 0 decoded_reg_input_selector [1:0] $end
$var reg 1 1 decoded_reg_write_enable $end
$var reg 4 2 decoded_rs_address [3:0] $end
$var reg 4 3 decoded_rt_address [3:0] $end
$var reg 1 4 enable $end
$var reg 8 5 lsu_out [7:0] $end
$var reg 1 6 reset $end
$var integer 32 7 tests_failed [31:0] $end
$var integer 32 8 tests_passed [31:0] $end
$scope module uut $end
$var wire 8 9 alu_out [7:0] $end
$var wire 8 : block_id [7:0] $end
$var wire 1 , clock $end
$var wire 3 ; core_state [2:0] $end
$var wire 8 < decoded_immediate [7:0] $end
$var wire 4 = decoded_rd_address [3:0] $end
$var wire 2 > decoded_reg_input_selector [1:0] $end
$var wire 1 1 decoded_reg_write_enable $end
$var wire 4 ? decoded_rs_address [3:0] $end
$var wire 4 @ decoded_rt_address [3:0] $end
$var wire 1 4 enable $end
$var wire 8 A lsu_out [7:0] $end
$var wire 1 6 reset $end
$var parameter 2 B ARITHMETIC $end
$var parameter 2 C CONSTANT $end
$var parameter 32 D DATA_BITS $end
$var parameter 2 E MEMORY $end
$var parameter 3 F REQUEST $end
$var parameter 32 G THREADS_PER_BLOCK $end
$var parameter 32 H THREAD_ID $end
$var parameter 3 I UPDATE $end
$var reg 8 J rs [7:0] $end
$var reg 8 K rt [7:0] $end
$var integer 32 L i [31:0] $end
$upscope $end
$scope task check_signal $end
$var reg 256 M label [255:0] $end
$var integer 32 N actual [31:0] $end
$var integer 32 O expected [31:0] $end
$upscope $end
$scope task read_rs $end
$var reg 4 P addr [3:0] $end
$upscope $end
$scope task read_rt $end
$var reg 4 Q addr [3:0] $end
$upscope $end
$scope task write_reg $end
$var reg 4 R rd [3:0] $end
$var reg 2 S src [1:0] $end
$var reg 8 T val_alu [7:0] $end
$var reg 8 U val_imm [7:0] $end
$var reg 8 V val_lsu [7:0] $end
$upscope $end
$upscope $end
$enddefinitions $end
$comment Show the parameter values. $end
$dumpall
b110 I
b10 H
b100 G
b11 F
b1 E
b1000 D
b10 C
b0 B
b110 )
b10 (
b100 '
b11 &
b1 %
b10 $
b0 #
$end
#0
$dumpvars
bx V
bx U
bx T
bx S
bx R
bx Q
bx P
bx O
bx N
bx M
bx L
bx K
bx J
b0 A
b0 @
b0 ?
b0 >
b0 =
b0 <
b0 ;
b0 :
b0 9
b0 8
b0 7
16
b0 5
04
b0 3
b0 2
01
b0 0
b0 /
b0 .
b0 -
0,
b0 +
b0 *
bx "
bx !
$end
#5
b0 !
b0 K
b0 "
b0 J
b1101 L
1,
#10
0,
#15
b1101 L
1,
#20
0,
14
06
#25
1,
#30
0,
b11 -
b11 ;
b1110 2
b1110 ?
b1110 P
#35
b100 "
b100 J
1,
#40
0,
b1111 2
b1111 ?
b1111 P
b1 8
b10000000101000001001010110001001101100011011110110001101101011010001000110100101101101001010010010000000111101001000000101010001001000010100100100010101000001010001000101001101011111010100000100010101010010010111110100001001001100010011110100001101001011 M
b100 O
b100 N
#45
b10 "
b10 J
1,
#50
0,
b1101 2
b1101 ?
b1101 P
b10 8
b110010101110100001110100010000001010010001100010011010100100000001010000010010101110100011010000111001001100101011000010110010001001001011001000111100000101001001000000011110100100000010101000100100001010010010001010100000101000100010111110100100101000100 M
b10 O
b10 N
#55
b0 "
b0 J
1,
#60
0,
b110 -
b110 ;
b101010 .
b101010 <
b10 0
b10 >
11
b101010 U
b0 V
b0 T
b10 S
b0 R
b11 8
b101001001100101011100110110010101110100001110100010000001010010001100010011001100100000001010000010010101100010011011000110111101100011011010110100100101100100011110000010100100100000001111010010000000110000 M
b0 O
b0 N
#65
1,
#70
0,
b11 -
b11 ;
b0 2
b0 ?
b0 P
01
#75
b101010 !
b101010 K
b101010 "
b101010 J
1,
#80
0,
b110 -
b110 ;
b11001000 .
b11001000 <
b111 /
b111 =
11
b11001000 U
b111 R
b100 8
b100001101001111010011100101001101010100001110100010000001010010001100000010000000111101001000000011010000110010 M
b101010 O
b101010 N
#85
1,
#90
0,
b11 -
b11 ;
b111 2
b111 ?
b111 P
01
#95
b11001000 "
b11001000 J
1,
#100
0,
b110 -
b110 ;
b0 .
b0 <
b1100011 *
b1100011 9
b0 0
b0 >
b1 /
b1 =
11
b0 U
b1100011 T
b0 S
b1 R
b101 8
b10000110100111101001110010100110101010000111010001000000101001000110111001000000011110100100000001100100011000000110000 M
b11001000 O
b11001000 N
#105
1,
#110
0,
b11 -
b11 ;
b1 2
b1 ?
b1 P
01
#115
b1100011 "
b1100011 J
1,
#120
0,
b110 -
b110 ;
b11111111 *
b11111111 9
b101 /
b101 =
11
b11111111 T
b101 R
b110 8
b10000010100110001010101001110100010000001010010001100010010000000111101001000000011100100111001 M
b1100011 O
b1100011 N
#125
1,
#130
0,
b11 -
b11 ;
b101 2
b101 ?
b101 P
01
#135
b11111111 "
b11111111 J
1,
#140
0,
b110 -
b110 ;
b10101101 5
b10101101 A
b0 *
b0 9
b1 0
b1 >
b10 /
b10 =
11
b10101101 V
b0 T
b1 S
b10 R
b111 8
b1000001010011000101010100111010001000000101001000110101001000000011110100100000001100100011010100110101 M
b11111111 O
b11111111 N
#145
1,
#150
0,
b11 -
b11 ;
b10 2
b10 ?
b10 P
01
#155
b10101101 "
b10101101 J
1,
#160
0,
b110 -
b110 ;
b1001101 .
b1001101 <
b0 5
b0 A
b10 0
b10 >
b11 /
b11 =
11
b1001101 U
b0 V
b10 S
b11 R
b1000 8
b1001101010001010100110100111010001000000101001000110010001000000011110100100000001100010011011100110011 M
b10101101 O
b10101101 N
#165
1,
#170
0,
b1011000 .
b1011000 <
b100 /
b100 =
b1011000 U
b100 R
11
#175
1,
#180
0,
b11 -
b11 ;
b100 3
b100 @
b11 2
b11 ?
01
#185
b1011000 !
b1011000 K
b1001101 "
b1001101 J
1,
#190
0,
b110 -
b110 ;
b1100011 .
b1100011 <
b1110 /
b1110 =
11
b1100011 U
b1110 R
b1010 8
b101010001110111011011110010110101101111011100000011101000100000011100100111010000100000001111010010000001010010001101000010000000111101001000000011100000111000 M
b1011000 O
b1011000 N
#195
1,
#200
0,
b11 -
b11 ;
b1110 2
b1110 ?
b1110 P
01
#205
b100 "
b100 J
1,
#210
0,
b110 -
b110 ;
b1111 /
b1111 =
11
b1111 R
b1011 8
b11000100110100001000000111010101101110011000110110100001100001011011100110011101100101011001000010000001100001011001100111010001100101011100100010000001110111011100100110100101110100011001010010000001100001011101000111010001100101011011010111000001110100 M
b100 O
b100 N
#215
1,
#220
0,
b11 -
b11 ;
b1111 2
b1111 ?
b1111 P
01
#225
b10 "
b10 J
1,
#230
0,
b0 -
b0 ;
b111 +
b111 :
b1100 8
b11000100110101001000000111010101101110011000110110100001100001011011100110011101100101011001000010000001100001011001100111010001100101011100100010000001110111011100100110100101110100011001010010000001100001011101000111010001100101011011010111000001110100 M
b10 O
b10 N
#235
1,
#240
0,
b11 -
b11 ;
b1101 2
b1101 ?
b1101 P
#245
b111 "
b111 J
1,
#250
0,
b1111 +
b1111 :
b1101 8
b10000100110110001101111011000110110101101001001010001000011101000100000010100100011000100110011001000000011110100100000011000100110110001101111011000110110101101011111011010010110010000100000001111010010000000110111 M
b111 O
b111 N
#255
1,
#260
0,
#265
b1111 "
b1111 J
1,
#270
0,
b0 2
b0 ?
b0 P
b1110 8
b100001001101100011011110110001101101011010010010100010000111010001000000101001000110001001100110010000001110101011100000110010001100001011101000110010101110011001000000111010001101111001000000011000100110101 M
b1111 O
b1111 N
#275
b101010 "
b101010 J
1,
#280
0,
b111 2
b111 ?
04
b1111 8
b100010101101110011000010110001001101100011001010010000001110011011001010111010001110101011100000011101000100000011100100111001100100000001111010010000001010010001100000010000000111101001000000011010000110010 M
b101010 O
b101010 N
#285
1,
#290
0,
14
b10000 8
b111010101110011001000000111011001100001011011000111010101100101001000000010100001101110011011110111010000100000011101010111000001100100011000010111010001100101011001000010000001110100011011110010000001010010001101110011110100110010001100000011000000101001 M
#295
b11001000 "
b11001000 J
1,
#300
0,
16
b10001 8
b100010101101110011000010110001001101100011001010011110100110001001110100010000001110010011100110010000001110101011100000110010001100001011101000110010101110011001000000111010001101111001000000101001000110111001000000011110100100000001100100011000000110000 M
b11001000 O
b11001000 N
#305
b0 !
b0 K
b0 "
b0 J
b1101 L
1,
#310
0,
b0 2
b0 ?
06
b10010 8
b101001001100101011100110110010101110100001110100010000001110010011100110010000001101111011101010111010001110000011101010111010000100000001111010010000000110000 M
b0 O
b0 N
#315
1,
#320
0,
b1110 2
b1110 ?
b1110 P
b10011 8
b1010010011001010111001101100101011101000011101000100000010100100011000000100000001111010010000000110000001000000110000101100110011101000110010101110010001000000111001001100101011100110110010101110100 M
#325
b100 "
b100 J
1,
#330
0,
b1111 2
b1111 ?
b1111 P
b10100 8
b11000100110100001000000111001001100101011100110111010001101111011100100110010101100100001000000111010001101111001000000101010001001000010100100100010101000001010001000101001101011111010100000100010101010010010111110100001001001100010011110100001101001011 M
b100 O
b100 N
#335
b10 "
b10 J
1,
#340
0,
b10101 8
b101001001100101011100110110010101110100001110100010000001010010001100010011010100100000011100100110010101110011011101000110111101110010011001010110010000100000011101000110111100100000010101000100100001010010010001010100000101000100010111110100100101000100 M
b10 O
b10 N
