src/scheduler.sv
`default_nettype none
`timescale 1ns/1ns

// SCHEDULER
// The core's control FSM. It walks every instruction through the 6 execution
// stages and broadcasts the current stage as `core_state` - the signal that
// gates the fetcher, decoder, register file, ALU, LSU and PC.
//
//   FETCH -> DECODE -> REQUEST -> WAIT -> EXECUTE -> UPDATE -> (FETCH | DONE)
//
// Two stages can stall:
//   FETCH : waits for `fetcher_done` (instruction back from program memory)
//   WAIT  : waits for every thread's LSU to finish any memory traffic
//
// All threads in the block are assumed to share control flow, so a single
// `current_pc` is kept and refreshed from the threads' `next_pc` in UPDATE.
module scheduler #(
    parameter THREADS_PER_BLOCK = 4
) (
    input  wire clock,
    input  wire reset,
    input  wire start,                           // Dispatcher: begin executing this block

    // Decoder signals that influence sequencing
    input  wire decoded_mem_read_enable,         // (informational) this is a LDR
    input  wire decoded_mem_write_enable,        // (informational) this is a STR
    input  wire decoded_ret,                      // RET: block is finished after UPDATE

    // Fetcher status
    input  wire fetcher_done,                     // Instruction has been fetched

    // Per-thread LSU status (busy while REQUESTING/WAITING)
    input  wire [1:0] lsu_state [THREADS_PER_BLOCK-1:0],

    // Program counter: scheduler owns current_pc, threads compute next_pc
    input  wire [7:0] next_pc [THREADS_PER_BLOCK-1:0],
    output reg  [7:0] current_pc,

    // Broadcast pipeline stage + block-complete flag
    output reg  [2:0] core_state,
    output reg        done
);

    // Canonical 3-bit pipeline encoding (shared with every core module)
    localparam IDLE    = 3'b000,
               FETCH   = 3'b001,
               DECODE  = 3'b010,
               REQUEST = 3'b011,
               WAIT    = 3'b100,
               EXECUTE = 3'b101,
               UPDATE  = 3'b110,
               DONE    = 3'b111;

    // LSU states that mean "memory still in flight"
    localparam LSU_REQUESTING = 2'b01,
               LSU_WAITING    = 2'b10;

    integer i;
    reg     any_lsu_busy;

    always @(posedge clock) begin
        if (reset) begin
            current_pc <= 8'b0;
            core_state <= IDLE;
            done       <= 1'b0;
        end else begin
            case (core_state)
                IDLE: begin
                    // Hold until the dispatcher launches this block
                    if (start) core_state <= FETCH;
                end

                FETCH: begin
                    // Wait for the instruction to come back from program memory
                    if (fetcher_done) core_state <= DECODE;
                end

                DECODE: begin
                    // Decoder latches this cycle; control signals ready next
                    core_state <= REQUEST;
                end

                REQUEST: begin
                    // Register operands read, LSUs armed for any memory op
                    core_state <= WAIT;
                end

                WAIT: begin
                    // Stall until no thread's LSU is mid-transaction
                    any_lsu_busy = 1'b0;
                    for (i = 0; i < THREADS_PER_BLOCK; i = i + 1) begin
                        if (lsu_state[i] == LSU_REQUESTING ||
                            lsu_state[i] == LSU_WAITING)
                            any_lsu_busy = 1'b1;
                    end
                    if (!any_lsu_busy) core_state <= EXECUTE;
                end

                EXECUTE: begin
                    // ALU result / loaded data is now available
                    core_state <= UPDATE;
                end

                UPDATE: begin
                    if (decoded_ret) begin
                        // RET: this block is finished
                        core_state <= DONE;
                        done       <= 1'b1;
                    end else begin
                        // Advance PC (threads assumed convergent) and loop
                        current_pc <= next_pc[THREADS_PER_BLOCK-1];
                        core_state <= FETCH;
                    end
                end

                DONE: begin
                    // Block complete - stay here until reset
                end
            endcase
        end
    end

endmodule

test/scheduler_tb.sv
`default_nettype none
`timescale 1ns/1ns

// SCHEDULER TESTBENCH
// Mocks the fetcher / LSU / PC signals and walks the scheduler through full
// instruction cycles, checking the stage sequence, the FETCH and WAIT stalls,
// the PC advance in UPDATE, and RET completion.
module scheduler_tb;
    localparam THREADS_PER_BLOCK = 4;

    reg        clock;
    reg        reset;
    reg        start;
    reg        decoded_mem_read_enable;
    reg        decoded_mem_write_enable;
    reg        decoded_ret;
    reg        fetcher_done;
    reg  [1:0] lsu_state [THREADS_PER_BLOCK-1:0];
    reg  [7:0] next_pc   [THREADS_PER_BLOCK-1:0];

    wire [7:0] current_pc;
    wire [2:0] core_state;
    wire       done;

    scheduler #(
        .THREADS_PER_BLOCK (THREADS_PER_BLOCK)
    ) uut (
        .clock                    (clock),
        .reset                    (reset),
        .start                    (start),
        .decoded_mem_read_enable  (decoded_mem_read_enable),
        .decoded_mem_write_enable (decoded_mem_write_enable),
        .decoded_ret              (decoded_ret),
        .fetcher_done             (fetcher_done),
        .lsu_state                (lsu_state),
        .next_pc                  (next_pc),
        .current_pc               (current_pc),
        .core_state               (core_state),
        .done                     (done)
    );

    // Clock generation: 10ns period
    always #5 clock = ~clock;

    // Pipeline stages (must match scheduler.sv)
    localparam IDLE    = 3'b000;
    localparam FETCH   = 3'b001;
    localparam DECODE  = 3'b010;
    localparam REQUEST = 3'b011;
    localparam WAIT    = 3'b100;
    localparam EXECUTE = 3'b101;
    localparam UPDATE  = 3'b110;
    localparam DONE    = 3'b111;

    localparam LSU_IDLE    = 2'b00;
    localparam LSU_WAITING = 2'b10;

    integer tests_passed = 0;
    integer tests_failed = 0;
    integer t;

    task check_signal;
        input integer actual;
        input integer expected;
        input [255:0] label;
        begin
            if (actual === expected) begin
                $display("[PASS] %s", label);
                tests_passed = tests_passed + 1;
            end else begin
                $display("[FAIL] %s: expected %0d, got %0d", label, expected, actual);
                tests_failed = tests_failed + 1;
            end
        end
    endtask

    // Advance exactly one clock (one rising edge)
    task tick;
        begin
            #10;
        end
    endtask

    initial begin
        $dumpfile("scheduler_tb.vcd");
        $dumpvars(0, scheduler_tb);

        clock                    = 0;
        reset                    = 1;
        start                    = 0;
        decoded_mem_read_enable  = 0;
        decoded_mem_write_enable = 0;
        decoded_ret              = 0;
        fetcher_done             = 0;
        for (t = 0; t < THREADS_PER_BLOCK; t = t + 1) begin
            lsu_state[t] = LSU_IDLE;
            next_pc[t]   = 8'd0;
        end

        $display("\n========================================");
        $display("Scheduler Testbench Starting");
        $display("========================================\n");

        // Reset
        #20;
        check_signal(core_state, IDLE, "Reset: core_state = IDLE");
        check_signal(current_pc, 0,    "Reset: current_pc = 0");
        check_signal(done,       0,    "Reset: done = 0");
        reset = 0;
        #10;

        // ==========================================
        // A full ALU-style instruction cycle (no memory, no RET)
        // ==========================================
        $display("\n--- Full cycle: IDLE -> ... -> FETCH ---\n");

        check_signal(core_state, IDLE, "Still IDLE before start");

        start = 1;
        tick;
        check_signal(core_state, FETCH, "start -> FETCH");

        // FETCH stalls until the fetcher is done
        fetcher_done = 0;
        tick;
        check_signal(core_state, FETCH, "FETCH stalls while fetcher not done");
        fetcher_done = 1;
        tick;
        check_signal(core_state, DECODE, "fetcher_done -> DECODE");

        tick;
        check_signal(core_state, REQUEST, "DECODE -> REQUEST");

        // Set the next PC the threads computed; UPDATE should latch it
        for (t = 0; t < THREADS_PER_BLOCK; t = t + 1) next_pc[t] = 8'd1;

        tick;
        check_signal(core_state, WAIT, "REQUEST -> WAIT");

        // No memory in flight -> WAIT passes straight through
        tick;
        check_signal(core_state, EXECUTE, "WAIT (no LSU busy) -> EXECUTE");

        tick;
        check_signal(core_state, UPDATE, "EXECUTE -> UPDATE");

        tick;
        check_signal(core_state, FETCH, "UPDATE (no RET) -> FETCH");
        check_signal(current_pc, 1,     "UPDATE advances current_pc to next_pc (1)");

        // ==========================================
        // Second cycle: a memory instruction stalls WAIT
        // ==========================================
        $display("\n--- WAIT stalls on a busy LSU ---\n");

        // already in FETCH with fetcher_done=1
        tick;  check_signal(core_state, DECODE,  "cycle2: -> DECODE");
        tick;  check_signal(core_state, REQUEST, "cycle2: -> REQUEST");

        // Thread 2 has a memory op in flight
        lsu_state[2] = LSU_WAITING;
        for (t = 0; t < THREADS_PER_BLOCK; t = t + 1) next_pc[t] = 8'd2;

        tick;  check_signal(core_state, WAIT, "cycle2: -> WAIT");
        tick;  check_signal(core_state, WAIT, "WAIT holds while LSU busy");
        tick;  check_signal(core_state, WAIT, "WAIT still holds");

        // Memory finishes
        lsu_state[2] = LSU_IDLE;
        tick;  check_signal(core_state, EXECUTE, "LSU idle -> EXECUTE");

        // ==========================================
        // RET ends the block
        // ==========================================
        $display("\n--- RET -> DONE ---\n");

        decoded_ret = 1;
        tick;  check_signal(core_state, UPDATE, "EXECUTE -> UPDATE");
        tick;
        check_signal(core_state, DONE, "UPDATE with RET -> DONE");
        check_signal(done,       1,    "done asserted");

        // DONE is sticky
        tick;
        check_signal(core_state, DONE, "DONE stays until reset");

        // ==========================================
        // Reset returns to IDLE
        // ==========================================
        $display("\n--- Reset clears state ---\n");

        reset = 1;
        #10;
        check_signal(core_state, IDLE, "Reset: core_state = IDLE");
        check_signal(done,       0,    "Reset: done = 0");
        reset = 0;

        // ==========================================
        // Summary
        // ==========================================
        #20;
        $display("\n========================================");
        $display("Test Summary");
        $display("========================================");
        $display("Passed: %d", tests_passed);
        $display("Failed: %d", tests_failed);
        $display("========================================\n");

        if (tests_failed == 0)
            $display("ALL TESTS PASSED!\n");
        else
            $display("SOME TESTS FAILED!\n");

        $finish;
    end

endmodule

test/scheduler_tb.vcd
$date
	Fri Jun  5 11:08:43 2026
$end
$version
	Icarus Verilog
$end
$timescale
	1ns
$end
$scope module scheduler_tb $end
$var wire 1 ! done $end
$var wire 8 " current_pc [7:0] $end
$var wire 3 # core_state [2:0] $end
$var parameter 3 $ DECODE $end
$var parameter 3 % DONE $end
$var parameter 3 & EXECUTE $end
$var parameter 3 ' FETCH $end
$var parameter 3 ( IDLE $end
$var parameter 2 ) LSU_IDLE $end
$var parameter 2 * LSU_WAITING $end
$var parameter 3 + REQUEST $end
$var parameter 32 , THREADS_PER_BLOCK $end
$var parameter 3 - UPDATE $end
$var parameter 3 . WAIT $end
$var reg 1 / clock $end
$var reg 1 0 decoded_mem_read_enable $end
$var reg 1 1 decoded_mem_write_enable $end
$var reg 1 2 decoded_ret $end
$var reg 1 3 fetcher_done $end
$var reg 1 4 reset $end
$var reg 1 5 start $end
$var integer 32 6 t [31:0] $end
$var integer 32 7 tests_failed [31:0] $end
$var integer 32 8 tests_passed [31:0] $end
$scope module uut $end
$var wire 1 / clock $end
$var wire 1 0 decoded_mem_read_enable $end
$var wire 1 1 decoded_mem_write_enable $end
$var wire 1 2 decoded_ret $end
$var wire 1 3 fetcher_done $end
$var wire 1 4 reset $end
$var wire 1 5 start $end
$var parameter 3 9 DECODE $end
$var parameter 3 : DONE $end
$var parameter 3 ; EXECUTE $end
$var parameter 3 < FETCH $end
$var parameter 3 = IDLE $end
$var parameter 2 > LSU_REQUESTING $end
$var parameter 2 ? LSU_WAITING $end
$var parameter 3 @ REQUEST $end
$var parameter 32 A THREADS_PER_BLOCK $end
$var parameter 3 B UPDATE $end
$var parameter 3 C WAIT $end
$var reg 1 D any_lsu_busy $end
$var reg 3 E core_state [2:0] $end
$var reg 8 F current_pc [7:0] $end
$var reg 1 ! done $end
$var integer 32 G i [31:0] $end
$upscope $end
$scope task check_signal $end
$var reg 256 H label [255:0] $end
$var integer 32 I actual [31:0] $end
$var integer 32 J expected [31:0] $end
$upscope $end
$scope task tick $end
$upscope $end
$upscope $end
$enddefinitions $end
$comment Show the parameter values. $end
$dumpall
b100 C
b110 B
b100 A
b11 @
b10 ?
b1 >
b0 =
b1 <
b101 ;
b111 :
b10 9
b100 .
b110 -
b100 ,
b11 +
b10 *
b0 )
b0 (
b1 '
b101 &
b111 %
b10 $
$end
#0
$dumpvars
bx J
bx I
bx H
bx G
bx F
bx E
xD
b0 8
b0 7
b100 6
05
14
03
02
01
00
0/
bx #
bx "
x!
$end
#5
0!
b0 #
b0 E
b0 "
b0 F
1/
#10
0/
#15
1/
#20
0/
04
b11 8
b10100100110010101110011011001010111010000111010001000000110010001101111011011100110010100100000001111010010000000110000 H
b0 J
b0 I
#25
1/
#30
0/
15
b100 8
b101001101110100011010010110110001101100001000000100100101000100010011000100010100100000011000100110010101100110011011110111001001100101001000000111001101110100011000010111001001110100 H
#35
b1 #
b1 E
1/
#40
0/
b101 8
b111001101110100011000010111001001110100001000000010110100111110001000000100011001000101010101000100001101001000 H
b1 J
b1 I
#45
1/
#50
0/
13
b110 8
b100001101001000001000000111001101110100011000010110110001101100011100110010000001110111011010000110100101101100011001010010000001100110011001010111010001100011011010000110010101110010001000000110111001101111011101000010000001100100011011110110111001100101 H
#55
b10 #
b10 E
1/
#60
0/
b111 8
b1100110011001010111010001100011011010000110010101110010010111110110010001101111011011100110010100100000001011010011111000100000010001000100010101000011010011110100010001000101 H
b10 J
b10 I
#65
b11 #
b11 E
1/
#70
0/
b100 6
b1000 8
b100010001000101010000110100111101000100010001010010000000101101001111100010000001010010010001010101000101010101010001010101001101010100 H
b11 J
b11 I
#75
b100 #
b100 E
1/
#80
0/
b1001 8
b10100100100010101010001010101010100010101010011010101000010000000101101001111100010000001010111010000010100100101010100 H
b100 J
b100 I
#85
b101 #
b101 E
b100 G
0D
1/
#90
0/
b1010 8
b101011101000001010010010101010000100000001010000110111001101111001000000100110001010011010101010010000001100010011101010111001101111001001010010010000000101101001111100010000001000101010110000100010101000011010101010101010001000101 H
b101 J
b101 I
#95
b110 #
b110 E
1/
#100
0/
b1011 8
b100010101011000010001010100001101010101010101000100010100100000001011010011111000100000010101010101000001000100010000010101010001000101 H
b110 J
b110 I
#105
b1 #
b1 E
b1 "
b1 F
1/
#110
0/
b1101 8
b111011001100001011011100110001101100101011100110010000001100011011101010111001001110010011001010110111001110100010111110111000001100011001000000111010001101111001000000110111001100101011110000111010001011111011100000110001100100000001010000011000100101001 H
b1 J
b1 I
#115
b10 #
b10 E
1/
#120
0/
b1110 8
b110001101111001011000110110110001100101001100100011101000100000001011010011111000100000010001000100010101000011010011110100010001000101 H
b10 J
b10 I
#125
b11 #
b11 E
1/
#130
0/
b100 6
b1111 8
b11000110111100101100011011011000110010100110010001110100010000000101101001111100010000001010010010001010101000101010101010001010101001101010100 H
b11 J
b11 I
#135
b100 #
b100 E
1/
#140
0/
b10000 8
b11000110111100101100011011011000110010100110010001110100010000000101101001111100010000001010111010000010100100101010100 H
b100 J
b100 I
#145
1D
b100 G
1/
#150
0/
b10001 8
b1010111010000010100100101010100001000000110100001101111011011000110010001110011001000000111011101101000011010010110110001100101001000000100110001010011010101010010000001100010011101010111001101111001 H
#155
b100 G
1D
1/
#160
0/
b10010 8
b1010111010000010100100101010100001000000111001101110100011010010110110001101100001000000110100001101111011011000110010001110011 H
#165
b101 #
b101 E
b100 G
0D
1/
#170
0/
12
b10011 8
b1001100010100110101010100100000011010010110010001101100011001010010000000101101001111100010000001000101010110000100010101000011010101010101010001000101 H
b101 J
b101 I
#175
b110 #
b110 E
1/
#180
0/
b10100 8
b100010101011000010001010100001101010101010101000100010100100000001011010011111000100000010101010101000001000100010000010101010001000101 H
b110 J
b110 I
#185
1!
b111 #
b111 E
1/
#190
0/
b10110 8
b1100100011011110110111001100101001000000110000101110011011100110110010101110010011101000110010101100100 H
b1 J
b1 I
#195
1/
#200
0/
14
b10111 8
b1000100010011110100111001000101001000000111001101110100011000010111100101110011001000000111010101101110011101000110100101101100001000000111001001100101011100110110010101110100 H
b111 J
b111 I
#205
0!
b0 #
b0 E
b0 "
b0 F
1/
#210
0/
04
b11001 8
b10100100110010101110011011001010111010000111010001000000110010001101111011011100110010100100000001111010010000000110000 H
b0 J
b0 I
#215
b1 #
b1 E
1/
#220
0/
#225
b10 #
b10 E
1/
